[{"line":2,"elements":[{"start_timestamp":"2024-02-22T17:45:17.670Z","before":[{"result":{"error_message":"io.github.bonigarcia.wdm.config.WebDriverManagerException: java.lang.NumberFormatException: For input string: \"public\"\n\tat io.github.bonigarcia.wdm.WebDriverManager.handleException(WebDriverManager.java:1445)\n\tat io.github.bonigarcia.wdm.WebDriverManager.manage(WebDriverManager.java:1205)\n\tat io.github.bonigarcia.wdm.WebDriverManager.fallback(WebDriverManager.java:1461)\n\tat io.github.bonigarcia.wdm.WebDriverManager.handleException(WebDriverManager.java:1442)\n\tat io.github.bonigarcia.wdm.WebDriverManager.manage(WebDriverManager.java:1205)\n\tat io.github.bonigarcia.wdm.WebDriverManager.handleException(WebDriverManager.java:1435)\n\tat io.github.bonigarcia.wdm.WebDriverManager.manage(WebDriverManager.java:1205)\n\tat io.github.bonigarcia.wdm.WebDriverManager.setup(WebDriverManager.java:427)\n\tat helper.Utility.startDriver(Utility.java:47)\n\tat stepDef.Hooks.beforeTest(Hooks.java:30)\nCaused by: java.lang.NumberFormatException: For input string: \"public\"\n\tat java.base/java.lang.NumberFormatException.forInputString(NumberFormatException.java:67)\n\tat java.base/java.lang.Integer.parseInt(Integer.java:662)\n\tat java.base/java.lang.Integer.parseInt(Integer.java:778)\n\tat io.github.bonigarcia.wdm.managers.ChromeDriverManager.buildUrl(ChromeDriverManager.java:178)\n\tat io.github.bonigarcia.wdm.managers.ChromeDriverManager.buildUrl(ChromeDriverManager.java:155)\n\tat io.github.bonigarcia.wdm.WebDriverManager.download(WebDriverManager.java:1282)\n\tat io.github.bonigarcia.wdm.WebDriverManager.manage(WebDriverManager.java:1199)\n\tat io.github.bonigarcia.wdm.WebDriverManager.fallback(WebDriverManager.java:1461)\n\tat io.github.bonigarcia.wdm.WebDriverManager.handleException(WebDriverManager.java:1442)\n\tat io.github.bonigarcia.wdm.WebDriverManager.manage(WebDriverManager.java:1205)\n\tat io.github.bonigarcia.wdm.WebDriverManager.handleException(WebDriverManager.java:1435)\n\tat io.github.bonigarcia.wdm.WebDriverManager.manage(WebDriverManager.java:1205)\n\tat io.github.bonigarcia.wdm.WebDriverManager.setup(WebDriverManager.java:427)\n\tat helper.Utility.startDriver(Utility.java:47)\n\tat stepDef.Hooks.beforeTest(Hooks.java:30)\n\tat java.base/jdk.internal.reflect.DirectMethodHandleAccessor.invoke(DirectMethodHandleAccessor.java:103)\n\tat java.base/java.lang.reflect.Method.invoke(Method.java:580)\n\tat io.cucumber.java.Invoker.doInvoke(Invoker.java:66)\n\tat io.cucumber.java.Invoker.invoke(Invoker.java:24)\n\tat io.cucumber.java.AbstractGlueDefinition.invokeMethod(AbstractGlueDefinition.java:47)\n\tat io.cucumber.java.JavaHookDefinition.execute(JavaHookDefinition.java:64)\n\tat io.cucumber.core.runner.CoreHookDefinition.execute(CoreHookDefinition.java:46)\n\tat io.cucumber.core.runner.HookDefinitionMatch.runStep(HookDefinitionMatch.java:21)\n\tat io.cucumber.core.runner.ExecutionMode$1.execute(ExecutionMode.java:10)\n\tat io.cucumber.core.runner.TestStep.executeStep(TestStep.java:84)\n\tat io.cucumber.core.runner.TestStep.run(TestStep.java:56)\n\tat io.cucumber.core.runner.TestCase.run(TestCase.java:78)\n\tat io.cucumber.core.runner.Runner.runPickle(Runner.java:75)\n\tat io.cucumber.core.runtime.Runtime.lambda$executePickle$6(Runtime.java:107)\n\tat io.cucumber.core.runtime.CucumberExecutionContext.lambda$runTestCase$5(CucumberExecutionContext.java:137)\n\tat io.cucumber.core.runtime.RethrowingThrowableCollector.executeAndThrow(RethrowingThrowableCollector.java:23)\n\tat io.cucumber.core.runtime.CucumberExecutionContext.runTestCase(CucumberExecutionContext.java:137)\n\tat io.cucumber.core.runtime.Runtime.lambda$executePickle$7(Runtime.java:107)\n\tat java.base/java.util.concurrent.Executors$RunnableAdapter.call(Executors.java:572)\n\tat java.base/java.util.concurrent.FutureTask.run(FutureTask.java:317)\n\tat io.cucumber.core.runtime.Runtime$SameThreadExecutorService.execute(Runtime.java:235)\n\tat java.base/java.util.concurrent.AbstractExecutorService.submit(AbstractExecutorService.java:123)\n\tat io.cucumber.core.runtime.Runtime.lambda$runFeatures$3(Runtime.java:89)\n\tat java.base/java.util.stream.ReferencePipeline$3$1.accept(ReferencePipeline.java:197)\n\tat java.base/java.util.stream.SliceOps$1$1.accept(SliceOps.java:200)\n\tat java.base/java.util.ArrayList$ArrayListSpliterator.tryAdvance(ArrayList.java:1685)\n\tat java.base/java.util.stream.ReferencePipeline.forEachWithCancel(ReferencePipeline.java:129)\n\tat java.base/java.util.stream.AbstractPipeline.copyIntoWithCancel(AbstractPipeline.java:527)\n\tat java.base/java.util.stream.AbstractPipeline.copyInto(AbstractPipeline.java:513)\n\tat java.base/java.util.stream.AbstractPipeline.wrapAndCopyInto(AbstractPipeline.java:499)\n\tat java.base/java.util.stream.ReduceOps$ReduceOp.evaluateSequential(ReduceOps.java:921)\n\tat java.base/java.util.stream.AbstractPipeline.evaluate(AbstractPipeline.java:234)\n\tat java.base/java.util.stream.ReferencePipeline.collect(ReferencePipeline.java:682)\n\tat io.cucumber.core.runtime.Runtime.runFeatures(Runtime.java:90)\n\tat io.cucumber.core.runtime.Runtime.lambda$run$0(Runtime.java:78)\n\tat io.cucumber.core.runtime.CucumberExecutionContext.lambda$runFeatures$6(CucumberExecutionContext.java:148)\n\tat io.cucumber.core.runtime.CucumberExecutionContext.execute(CucumberExecutionContext.java:163)\n\tat io.cucumber.core.runtime.CucumberExecutionContext.runFeatures(CucumberExecutionContext.java:146)\n\tat io.cucumber.core.runtime.Runtime.run(Runtime.java:78)\n\tat io.cucumber.core.cli.Main.run(Main.java:87)\n\tat io.cucumber.core.cli.Main.main(Main.java:30)\n","duration":1096923635,"status":"failed"},"match":{"location":"stepDef.Hooks.beforeTest(io.cucumber.java.Scenario)"}}],"line":5,"name":"Test sign up normal","description":"","id":"test-automation-web;test-sign-up-normal","after":[{"result":{"error_message":"java.lang.NullPointerException: Cannot invoke \"org.openqa.selenium.WebDriver.quit()\" because \"helper.Utility.driver\" is null\n\tat helper.Utility.quitDriver(Utility.java:56)\n\tat stepDef.Hooks.afterTest(Hooks.java:39)\n","duration":2001008675,"status":"failed"},"match":{"location":"stepDef.Hooks.afterTest(io.cucumber.java.Scenario)"}}],"type":"scenario","keyword":"Scenario","steps":[{"result":{"duration":115916,"status":"skipped"},"line":6,"name":"user go to web page","match":{"location":"stepDef.WebStep.userGoToWebPage()"},"keyword":"Given "},{"result":{"duration":70341,"status":"skipped"},"line":7,"name":"user click sign up menu","match":{"location":"stepDef.WebStep.userClickSignUpMenu()"},"keyword":"And "},{"result":{"duration":65713,"status":"skipped"},"line":8,"name":"user input sign up username","match":{"location":"stepDef.WebStep.userInputSignUpUsername()"},"keyword":"And "},{"result":{"duration":64048,"status":"skipped"},"line":9,"name":"user input sign up pwd","match":{"location":"stepDef.WebStep.userInputSignUpPwd()"},"keyword":"And "},{"result":{"duration":61133,"status":"skipped"},"line":10,"name":"user click sign up button","match":{"location":"stepDef.WebStep.userClickSignUpButton()"},"keyword":"When "},{"result":{"duration":61825,"status":"skipped"},"line":11,"name":"validation get \"alert\" message \"Sign up successful.\"","match":{"arguments":[{"val":"\"alert\"","offset":15},{"val":"\"Sign up successful.\"","offset":31}],"location":"stepDef.WebStep.validationGetMessage(java.lang.String,java.lang.String)"},"keyword":"Then "}],"tags":[{"name":"@web"},{"name":"@web"}]},{"start_timestamp":"2024-02-22T17:45:20.797Z","before":[{"result":{"error_message":"io.github.bonigarcia.wdm.config.WebDriverManagerException: java.lang.NumberFormatException: For input string: \"public\"\n\tat io.github.bonigarcia.wdm.WebDriverManager.handleException(WebDriverManager.java:1445)\n\tat io.github.bonigarcia.wdm.WebDriverManager.manage(WebDriverManager.java:1205)\n\tat io.github.bonigarcia.wdm.WebDriverManager.fallback(WebDriverManager.java:1461)\n\tat io.github.bonigarcia.wdm.WebDriverManager.handleException(WebDriverManager.java:1442)\n\tat io.github.bonigarcia.wdm.WebDriverManager.manage(WebDriverManager.java:1205)\n\tat io.github.bonigarcia.wdm.WebDriverManager.handleException(WebDriverManager.java:1435)\n\tat io.github.bonigarcia.wdm.WebDriverManager.manage(WebDriverManager.java:1205)\n\tat io.github.bonigarcia.wdm.WebDriverManager.setup(WebDriverManager.java:427)\n\tat helper.Utility.startDriver(Utility.java:47)\n\tat stepDef.Hooks.beforeTest(Hooks.java:30)\nCaused by: java.lang.NumberFormatException: For input string: \"public\"\n\tat java.base/java.lang.NumberFormatException.forInputString(NumberFormatException.java:67)\n\tat java.base/java.lang.Integer.parseInt(Integer.java:662)\n\tat java.base/java.lang.Integer.parseInt(Integer.java:778)\n\tat io.github.bonigarcia.wdm.managers.ChromeDriverManager.buildUrl(ChromeDriverManager.java:178)\n\tat io.github.bonigarcia.wdm.managers.ChromeDriverManager.buildUrl(ChromeDriverManager.java:155)\n\tat io.github.bonigarcia.wdm.WebDriverManager.download(WebDriverManager.java:1282)\n\tat io.github.bonigarcia.wdm.WebDriverManager.manage(WebDriverManager.java:1199)\n\tat io.github.bonigarcia.wdm.WebDriverManager.fallback(WebDriverManager.java:1461)\n\tat io.github.bonigarcia.wdm.WebDriverManager.handleException(WebDriverManager.java:1442)\n\tat io.github.bonigarcia.wdm.WebDriverManager.manage(WebDriverManager.java:1205)\n\tat io.github.bonigarcia.wdm.WebDriverManager.handleException(WebDriverManager.java:1435)\n\tat io.github.bonigarcia.wdm.WebDriverManager.manage(WebDriverManager.java:1205)\n\tat io.github.bonigarcia.wdm.WebDriverManager.setup(WebDriverManager.java:427)\n\tat helper.Utility.startDriver(Utility.java:47)\n\tat stepDef.Hooks.beforeTest(Hooks.java:30)\n\tat java.base/jdk.internal.reflect.DirectMethodHandleAccessor.invoke(DirectMethodHandleAccessor.java:103)\n\tat java.base/java.lang.reflect.Method.invoke(Method.java:580)\n\tat io.cucumber.java.Invoker.doInvoke(Invoker.java:66)\n\tat io.cucumber.java.Invoker.invoke(Invoker.java:24)\n\tat io.cucumber.java.AbstractGlueDefinition.invokeMethod(AbstractGlueDefinition.java:47)\n\tat io.cucumber.java.JavaHookDefinition.execute(JavaHookDefinition.java:64)\n\tat io.cucumber.core.runner.CoreHookDefinition.execute(CoreHookDefinition.java:46)\n\tat io.cucumber.core.runner.HookDefinitionMatch.runStep(HookDefinitionMatch.java:21)\n\tat io.cucumber.core.runner.ExecutionMode$1.execute(ExecutionMode.java:10)\n\tat io.cucumber.core.runner.TestStep.executeStep(TestStep.java:84)\n\tat io.cucumber.core.runner.TestStep.run(TestStep.java:56)\n\tat io.cucumber.core.runner.TestCase.run(TestCase.java:78)\n\tat io.cucumber.core.runner.Runner.runPickle(Runner.java:75)\n\tat io.cucumber.core.runtime.Runtime.lambda$executePickle$6(Runtime.java:107)\n\tat io.cucumber.core.runtime.CucumberExecutionContext.lambda$runTestCase$5(CucumberExecutionContext.java:137)\n\tat io.cucumber.core.runtime.RethrowingThrowableCollector.executeAndThrow(RethrowingThrowableCollector.java:23)\n\tat io.cucumber.core.runtime.CucumberExecutionContext.runTestCase(CucumberExecutionContext.java:137)\n\tat io.cucumber.core.runtime.Runtime.lambda$executePickle$7(Runtime.java:107)\n\tat java.base/java.util.concurrent.Executors$RunnableAdapter.call(Executors.java:572)\n\tat java.base/java.util.concurrent.FutureTask.run(FutureTask.java:317)\n\tat io.cucumber.core.runtime.Runtime$SameThreadExecutorService.execute(Runtime.java:235)\n\tat java.base/java.util.concurrent.AbstractExecutorService.submit(AbstractExecutorService.java:123)\n\tat io.cucumber.core.runtime.Runtime.lambda$runFeatures$3(Runtime.java:89)\n\tat java.base/java.util.stream.ReferencePipeline$3$1.accept(ReferencePipeline.java:197)\n\tat java.base/java.util.stream.SliceOps$1$1.accept(SliceOps.java:200)\n\tat java.base/java.util.ArrayList$ArrayListSpliterator.tryAdvance(ArrayList.java:1685)\n\tat java.base/java.util.stream.ReferencePipeline.forEachWithCancel(ReferencePipeline.java:129)\n\tat java.base/java.util.stream.AbstractPipeline.copyIntoWithCancel(AbstractPipeline.java:527)\n\tat java.base/java.util.stream.AbstractPipeline.copyInto(AbstractPipeline.java:513)\n\tat java.base/java.util.stream.AbstractPipeline.wrapAndCopyInto(AbstractPipeline.java:499)\n\tat java.base/java.util.stream.ReduceOps$ReduceOp.evaluateSequential(ReduceOps.java:921)\n\tat java.base/java.util.stream.AbstractPipeline.evaluate(AbstractPipeline.java:234)\n\tat java.base/java.util.stream.ReferencePipeline.collect(ReferencePipeline.java:682)\n\tat io.cucumber.core.runtime.Runtime.runFeatures(Runtime.java:90)\n\tat io.cucumber.core.runtime.Runtime.lambda$run$0(Runtime.java:78)\n\tat io.cucumber.core.runtime.CucumberExecutionContext.lambda$runFeatures$6(CucumberExecutionContext.java:148)\n\tat io.cucumber.core.runtime.CucumberExecutionContext.execute(CucumberExecutionContext.java:163)\n\tat io.cucumber.core.runtime.CucumberExecutionContext.runFeatures(CucumberExecutionContext.java:146)\n\tat io.cucumber.core.runtime.Runtime.run(Runtime.java:78)\n\tat io.cucumber.core.cli.Main.run(Main.java:87)\n\tat io.cucumber.core.cli.Main.main(Main.java:30)\n","duration":331613734,"status":"failed"},"match":{"location":"stepDef.Hooks.beforeTest(io.cucumber.java.Scenario)"}}],"line":14,"name":"Test negative sign up user not input sign up username and password","description":"","id":"test-automation-web;test-negative-sign-up-user-not-input-sign-up-username-and-password","after":[{"result":{"error_message":"java.lang.NullPointerException: Cannot invoke \"org.openqa.selenium.WebDriver.quit()\" because \"helper.Utility.driver\" is null\n\tat helper.Utility.quitDriver(Utility.java:56)\n\tat stepDef.Hooks.afterTest(Hooks.java:39)\n","duration":2000767036,"status":"failed"},"match":{"location":"stepDef.Hooks.afterTest(io.cucumber.java.Scenario)"}}],"type":"scenario","keyword":"Scenario","steps":[{"result":{"duration":142315,"status":"skipped"},"line":15,"name":"user go to web page","match":{"location":"stepDef.WebStep.userGoToWebPage()"},"keyword":"Given "},{"result":{"duration":69770,"status":"skipped"},"line":16,"name":"user click sign up menu","match":{"location":"stepDef.WebStep.userClickSignUpMenu()"},"keyword":"And "},{"result":{"duration":64951,"status":"skipped"},"line":17,"name":"user click sign up button","match":{"location":"stepDef.WebStep.userClickSignUpButton()"},"keyword":"When "},{"result":{"duration":72314,"status":"skipped"},"line":18,"name":"validation get \"alert\" message \"Please fill out Username and Password.\"","match":{"arguments":[{"val":"\"alert\"","offset":15},{"val":"\"Please fill out Username and Password.\"","offset":31}],"location":"stepDef.WebStep.validationGetMessage(java.lang.String,java.lang.String)"},"keyword":"Then "}],"tags":[{"name":"@web"},{"name":"@web"}]},{"start_timestamp":"2024-02-22T17:45:23.143Z","before":[{"result":{"error_message":"io.github.bonigarcia.wdm.config.WebDriverManagerException: java.lang.NumberFormatException: For input string: \"public\"\n\tat io.github.bonigarcia.wdm.WebDriverManager.handleException(WebDriverManager.java:1445)\n\tat io.github.bonigarcia.wdm.WebDriverManager.manage(WebDriverManager.java:1205)\n\tat io.github.bonigarcia.wdm.WebDriverManager.fallback(WebDriverManager.java:1461)\n\tat io.github.bonigarcia.wdm.WebDriverManager.handleException(WebDriverManager.java:1442)\n\tat io.github.bonigarcia.wdm.WebDriverManager.manage(WebDriverManager.java:1205)\n\tat io.github.bonigarcia.wdm.WebDriverManager.handleException(WebDriverManager.java:1435)\n\tat io.github.bonigarcia.wdm.WebDriverManager.manage(WebDriverManager.java:1205)\n\tat io.github.bonigarcia.wdm.WebDriverManager.setup(WebDriverManager.java:427)\n\tat helper.Utility.startDriver(Utility.java:47)\n\tat stepDef.Hooks.beforeTest(Hooks.java:30)\nCaused by: java.lang.NumberFormatException: For input string: \"public\"\n\tat java.base/java.lang.NumberFormatException.forInputString(NumberFormatException.java:67)\n\tat java.base/java.lang.Integer.parseInt(Integer.java:662)\n\tat java.base/java.lang.Integer.parseInt(Integer.java:778)\n\tat io.github.bonigarcia.wdm.managers.ChromeDriverManager.buildUrl(ChromeDriverManager.java:178)\n\tat io.github.bonigarcia.wdm.managers.ChromeDriverManager.buildUrl(ChromeDriverManager.java:155)\n\tat io.github.bonigarcia.wdm.WebDriverManager.download(WebDriverManager.java:1282)\n\tat io.github.bonigarcia.wdm.WebDriverManager.manage(WebDriverManager.java:1199)\n\tat io.github.bonigarcia.wdm.WebDriverManager.fallback(WebDriverManager.java:1461)\n\tat io.github.bonigarcia.wdm.WebDriverManager.handleException(WebDriverManager.java:1442)\n\tat io.github.bonigarcia.wdm.WebDriverManager.manage(WebDriverManager.java:1205)\n\tat io.github.bonigarcia.wdm.WebDriverManager.handleException(WebDriverManager.java:1435)\n\tat io.github.bonigarcia.wdm.WebDriverManager.manage(WebDriverManager.java:1205)\n\tat io.github.bonigarcia.wdm.WebDriverManager.setup(WebDriverManager.java:427)\n\tat helper.Utility.startDriver(Utility.java:47)\n\tat stepDef.Hooks.beforeTest(Hooks.java:30)\n\tat java.base/jdk.internal.reflect.DirectMethodHandleAccessor.invoke(DirectMethodHandleAccessor.java:103)\n\tat java.base/java.lang.reflect.Method.invoke(Method.java:580)\n\tat io.cucumber.java.Invoker.doInvoke(Invoker.java:66)\n\tat io.cucumber.java.Invoker.invoke(Invoker.java:24)\n\tat io.cucumber.java.AbstractGlueDefinition.invokeMethod(AbstractGlueDefinition.java:47)\n\tat io.cucumber.java.JavaHookDefinition.execute(JavaHookDefinition.java:64)\n\tat io.cucumber.core.runner.CoreHookDefinition.execute(CoreHookDefinition.java:46)\n\tat io.cucumber.core.runner.HookDefinitionMatch.runStep(HookDefinitionMatch.java:21)\n\tat io.cucumber.core.runner.ExecutionMode$1.execute(ExecutionMode.java:10)\n\tat io.cucumber.core.runner.TestStep.executeStep(TestStep.java:84)\n\tat io.cucumber.core.runner.TestStep.run(TestStep.java:56)\n\tat io.cucumber.core.runner.TestCase.run(TestCase.java:78)\n\tat io.cucumber.core.runner.Runner.runPickle(Runner.java:75)\n\tat io.cucumber.core.runtime.Runtime.lambda$executePickle$6(Runtime.java:107)\n\tat io.cucumber.core.runtime.CucumberExecutionContext.lambda$runTestCase$5(CucumberExecutionContext.java:137)\n\tat io.cucumber.core.runtime.RethrowingThrowableCollector.executeAndThrow(RethrowingThrowableCollector.java:23)\n\tat io.cucumber.core.runtime.CucumberExecutionContext.runTestCase(CucumberExecutionContext.java:137)\n\tat io.cucumber.core.runtime.Runtime.lambda$executePickle$7(Runtime.java:107)\n\tat java.base/java.util.concurrent.Executors$RunnableAdapter.call(Executors.java:572)\n\tat java.base/java.util.concurrent.FutureTask.run(FutureTask.java:317)\n\tat io.cucumber.core.runtime.Runtime$SameThreadExecutorService.execute(Runtime.java:235)\n\tat java.base/java.util.concurrent.AbstractExecutorService.submit(AbstractExecutorService.java:123)\n\tat io.cucumber.core.runtime.Runtime.lambda$runFeatures$3(Runtime.java:89)\n\tat java.base/java.util.stream.ReferencePipeline$3$1.accept(ReferencePipeline.java:197)\n\tat java.base/java.util.stream.SliceOps$1$1.accept(SliceOps.java:200)\n\tat java.base/java.util.ArrayList$ArrayListSpliterator.tryAdvance(ArrayList.java:1685)\n\tat java.base/java.util.stream.ReferencePipeline.forEachWithCancel(ReferencePipeline.java:129)\n\tat java.base/java.util.stream.AbstractPipeline.copyIntoWithCancel(AbstractPipeline.java:527)\n\tat java.base/java.util.stream.AbstractPipeline.copyInto(AbstractPipeline.java:513)\n\tat java.base/java.util.stream.AbstractPipeline.wrapAndCopyInto(AbstractPipeline.java:499)\n\tat java.base/java.util.stream.ReduceOps$ReduceOp.evaluateSequential(ReduceOps.java:921)\n\tat java.base/java.util.stream.AbstractPipeline.evaluate(AbstractPipeline.java:234)\n\tat java.base/java.util.stream.ReferencePipeline.collect(ReferencePipeline.java:682)\n\tat io.cucumber.core.runtime.Runtime.runFeatures(Runtime.java:90)\n\tat io.cucumber.core.runtime.Runtime.lambda$run$0(Runtime.java:78)\n\tat io.cucumber.core.runtime.CucumberExecutionContext.lambda$runFeatures$6(CucumberExecutionContext.java:148)\n\tat io.cucumber.core.runtime.CucumberExecutionContext.execute(CucumberExecutionContext.java:163)\n\tat io.cucumber.core.runtime.CucumberExecutionContext.runFeatures(CucumberExecutionContext.java:146)\n\tat io.cucumber.core.runtime.Runtime.run(Runtime.java:78)\n\tat io.cucumber.core.cli.Main.run(Main.java:87)\n\tat io.cucumber.core.cli.Main.main(Main.java:30)\n","duration":334040769,"status":"failed"},"match":{"location":"stepDef.Hooks.beforeTest(io.cucumber.java.Scenario)"}}],"line":21,"name":"Test login normal","description":"","id":"test-automation-web;test-login-normal","after":[{"result":{"error_message":"java.lang.NullPointerException: Cannot invoke \"org.openqa.selenium.WebDriver.quit()\" because \"helper.Utility.driver\" is null\n\tat helper.Utility.quitDriver(Utility.java:56)\n\tat stepDef.Hooks.afterTest(Hooks.java:39)\n","duration":2000653955,"status":"failed"},"match":{"location":"stepDef.Hooks.afterTest(io.cucumber.java.Scenario)"}}],"type":"scenario","keyword":"Scenario","steps":[{"result":{"duration":101489,"status":"skipped"},"line":22,"name":"user go to web page","match":{"location":"stepDef.WebStep.userGoToWebPage()"},"keyword":"Given "},{"result":{"duration":58970,"status":"skipped"},"line":23,"name":"user click sign up menu","match":{"location":"stepDef.WebStep.userClickSignUpMenu()"},"keyword":"And "},{"result":{"duration":56275,"status":"skipped"},"line":24,"name":"user input sign up username","match":{"location":"stepDef.WebStep.userInputSignUpUsername()"},"keyword":"And "},{"result":{"duration":54843,"status":"skipped"},"line":25,"name":"user input sign up pwd","match":{"location":"stepDef.WebStep.userInputSignUpPwd()"},"keyword":"And "},{"result":{"duration":63729,"status":"skipped"},"line":26,"name":"user click sign up button","match":{"location":"stepDef.WebStep.userClickSignUpButton()"},"keyword":"When "},{"result":{"duration":55192,"status":"skipped"},"line":27,"name":"validation get \"alert\" message \"Sign up successful.\"","match":{"arguments":[{"val":"\"alert\"","offset":15},{"val":"\"Sign up successful.\"","offset":31}],"location":"stepDef.WebStep.validationGetMessage(java.lang.String,java.lang.String)"},"keyword":"Then "},{"result":{"duration":58990,"status":"skipped"},"line":28,"name":"user click login menu","match":{"location":"stepDef.WebStep.userClickLoginMenu()"},"keyword":"And "},{"result":{"duration":57767,"status":"skipped"},"line":29,"name":"user input login username","match":{"location":"stepDef.WebStep.userInputLoginUsername()"},"keyword":"And "},{"result":{"duration":53389,"status":"skipped"},"line":30,"name":"user input login pwd","match":{"location":"stepDef.WebStep.userInputLoginPwd()"},"keyword":"And "},{"result":{"duration":54772,"status":"skipped"},"line":31,"name":"user click login button","match":{"location":"stepDef.WebStep.userClickLoginButton()"},"keyword":"When "},{"result":{"duration":59681,"status":"skipped"},"line":32,"name":"validation login successful","match":{"location":"stepDef.WebStep.validationLoginSuccessful()"},"keyword":"Then "}],"tags":[{"name":"@web"},{"name":"@web"}]},{"start_timestamp":"2024-02-22T17:45:25.489Z","before":[{"result":{"error_message":"io.github.bonigarcia.wdm.config.WebDriverManagerException: java.lang.NumberFormatException: For input string: \"public\"\n\tat io.github.bonigarcia.wdm.WebDriverManager.handleException(WebDriverManager.java:1445)\n\tat io.github.bonigarcia.wdm.WebDriverManager.manage(WebDriverManager.java:1205)\n\tat io.github.bonigarcia.wdm.WebDriverManager.fallback(WebDriverManager.java:1461)\n\tat io.github.bonigarcia.wdm.WebDriverManager.handleException(WebDriverManager.java:1442)\n\tat io.github.bonigarcia.wdm.WebDriverManager.manage(WebDriverManager.java:1205)\n\tat io.github.bonigarcia.wdm.WebDriverManager.handleException(WebDriverManager.java:1435)\n\tat io.github.bonigarcia.wdm.WebDriverManager.manage(WebDriverManager.java:1205)\n\tat io.github.bonigarcia.wdm.WebDriverManager.setup(WebDriverManager.java:427)\n\tat helper.Utility.startDriver(Utility.java:47)\n\tat stepDef.Hooks.beforeTest(Hooks.java:30)\nCaused by: java.lang.NumberFormatException: For input string: \"public\"\n\tat java.base/java.lang.NumberFormatException.forInputString(NumberFormatException.java:67)\n\tat java.base/java.lang.Integer.parseInt(Integer.java:662)\n\tat java.base/java.lang.Integer.parseInt(Integer.java:778)\n\tat io.github.bonigarcia.wdm.managers.ChromeDriverManager.buildUrl(ChromeDriverManager.java:178)\n\tat io.github.bonigarcia.wdm.managers.ChromeDriverManager.buildUrl(ChromeDriverManager.java:155)\n\tat io.github.bonigarcia.wdm.WebDriverManager.download(WebDriverManager.java:1282)\n\tat io.github.bonigarcia.wdm.WebDriverManager.manage(WebDriverManager.java:1199)\n\tat io.github.bonigarcia.wdm.WebDriverManager.fallback(WebDriverManager.java:1461)\n\tat io.github.bonigarcia.wdm.WebDriverManager.handleException(WebDriverManager.java:1442)\n\tat io.github.bonigarcia.wdm.WebDriverManager.manage(WebDriverManager.java:1205)\n\tat io.github.bonigarcia.wdm.WebDriverManager.handleException(WebDriverManager.java:1435)\n\tat io.github.bonigarcia.wdm.WebDriverManager.manage(WebDriverManager.java:1205)\n\tat io.github.bonigarcia.wdm.WebDriverManager.setup(WebDriverManager.java:427)\n\tat helper.Utility.startDriver(Utility.java:47)\n\tat stepDef.Hooks.beforeTest(Hooks.java:30)\n\tat java.base/jdk.internal.reflect.DirectMethodHandleAccessor.invoke(DirectMethodHandleAccessor.java:103)\n\tat java.base/java.lang.reflect.Method.invoke(Method.java:580)\n\tat io.cucumber.java.Invoker.doInvoke(Invoker.java:66)\n\tat io.cucumber.java.Invoker.invoke(Invoker.java:24)\n\tat io.cucumber.java.AbstractGlueDefinition.invokeMethod(AbstractGlueDefinition.java:47)\n\tat io.cucumber.java.JavaHookDefinition.execute(JavaHookDefinition.java:64)\n\tat io.cucumber.core.runner.CoreHookDefinition.execute(CoreHookDefinition.java:46)\n\tat io.cucumber.core.runner.HookDefinitionMatch.runStep(HookDefinitionMatch.java:21)\n\tat io.cucumber.core.runner.ExecutionMode$1.execute(ExecutionMode.java:10)\n\tat io.cucumber.core.runner.TestStep.executeStep(TestStep.java:84)\n\tat io.cucumber.core.runner.TestStep.run(TestStep.java:56)\n\tat io.cucumber.core.runner.TestCase.run(TestCase.java:78)\n\tat io.cucumber.core.runner.Runner.runPickle(Runner.java:75)\n\tat io.cucumber.core.runtime.Runtime.lambda$executePickle$6(Runtime.java:107)\n\tat io.cucumber.core.runtime.CucumberExecutionContext.lambda$runTestCase$5(CucumberExecutionContext.java:137)\n\tat io.cucumber.core.runtime.RethrowingThrowableCollector.executeAndThrow(RethrowingThrowableCollector.java:23)\n\tat io.cucumber.core.runtime.CucumberExecutionContext.runTestCase(CucumberExecutionContext.java:137)\n\tat io.cucumber.core.runtime.Runtime.lambda$executePickle$7(Runtime.java:107)\n\tat java.base/java.util.concurrent.Executors$RunnableAdapter.call(Executors.java:572)\n\tat java.base/java.util.concurrent.FutureTask.run(FutureTask.java:317)\n\tat io.cucumber.core.runtime.Runtime$SameThreadExecutorService.execute(Runtime.java:235)\n\tat java.base/java.util.concurrent.AbstractExecutorService.submit(AbstractExecutorService.java:123)\n\tat io.cucumber.core.runtime.Runtime.lambda$runFeatures$3(Runtime.java:89)\n\tat java.base/java.util.stream.ReferencePipeline$3$1.accept(ReferencePipeline.java:197)\n\tat java.base/java.util.stream.SliceOps$1$1.accept(SliceOps.java:200)\n\tat java.base/java.util.ArrayList$ArrayListSpliterator.tryAdvance(ArrayList.java:1685)\n\tat java.base/java.util.stream.ReferencePipeline.forEachWithCancel(ReferencePipeline.java:129)\n\tat java.base/java.util.stream.AbstractPipeline.copyIntoWithCancel(AbstractPipeline.java:527)\n\tat java.base/java.util.stream.AbstractPipeline.copyInto(AbstractPipeline.java:513)\n\tat java.base/java.util.stream.AbstractPipeline.wrapAndCopyInto(AbstractPipeline.java:499)\n\tat java.base/java.util.stream.ReduceOps$ReduceOp.evaluateSequential(ReduceOps.java:921)\n\tat java.base/java.util.stream.AbstractPipeline.evaluate(AbstractPipeline.java:234)\n\tat java.base/java.util.stream.ReferencePipeline.collect(ReferencePipeline.java:682)\n\tat io.cucumber.core.runtime.Runtime.runFeatures(Runtime.java:90)\n\tat io.cucumber.core.runtime.Runtime.lambda$run$0(Runtime.java:78)\n\tat io.cucumber.core.runtime.CucumberExecutionContext.lambda$runFeatures$6(CucumberExecutionContext.java:148)\n\tat io.cucumber.core.runtime.CucumberExecutionContext.execute(CucumberExecutionContext.java:163)\n\tat io.cucumber.core.runtime.CucumberExecutionContext.runFeatures(CucumberExecutionContext.java:146)\n\tat io.cucumber.core.runtime.Runtime.run(Runtime.java:78)\n\tat io.cucumber.core.cli.Main.run(Main.java:87)\n\tat io.cucumber.core.cli.Main.main(Main.java:30)\n","duration":319864121,"status":"failed"},"match":{"location":"stepDef.Hooks.beforeTest(io.cucumber.java.Scenario)"}}],"line":35,"name":"Test negative login user not input login username and password","description":"","id":"test-automation-web;test-negative-login-user-not-input-login-username-and-password","after":[{"result":{"error_message":"java.lang.NullPointerException: Cannot invoke \"org.openqa.selenium.WebDriver.quit()\" because \"helper.Utility.driver\" is null\n\tat helper.Utility.quitDriver(Utility.java:56)\n\tat stepDef.Hooks.afterTest(Hooks.java:39)\n","duration":2000570408,"status":"failed"},"match":{"location":"stepDef.Hooks.afterTest(io.cucumber.java.Scenario)"}}],"type":"scenario","keyword":"Scenario","steps":[{"result":{"duration":68347,"status":"skipped"},"line":36,"name":"user go to web page","match":{"location":"stepDef.WebStep.userGoToWebPage()"},"keyword":"Given "},{"result":{"duration":46898,"status":"skipped"},"line":37,"name":"user click login menu","match":{"location":"stepDef.WebStep.userClickLoginMenu()"},"keyword":"And "},{"result":{"duration":57307,"status":"skipped"},"line":38,"name":"user click login button","match":{"location":"stepDef.WebStep.userClickLoginButton()"},"keyword":"When "},{"result":{"duration":46606,"status":"skipped"},"line":39,"name":"validation get \"alert\" message \"Please fill out Username and Password.\"","match":{"arguments":[{"val":"\"alert\"","offset":15},{"val":"\"Please fill out Username and Password.\"","offset":31}],"location":"stepDef.WebStep.validationGetMessage(java.lang.String,java.lang.String)"},"keyword":"Then "}],"tags":[{"name":"@web"},{"name":"@web"}]},{"start_timestamp":"2024-02-22T17:45:27.817Z","before":[{"result":{"error_message":"io.github.bonigarcia.wdm.config.WebDriverManagerException: java.lang.NumberFormatException: For input string: \"public\"\n\tat io.github.bonigarcia.wdm.WebDriverManager.handleException(WebDriverManager.java:1445)\n\tat io.github.bonigarcia.wdm.WebDriverManager.manage(WebDriverManager.java:1205)\n\tat io.github.bonigarcia.wdm.WebDriverManager.fallback(WebDriverManager.java:1461)\n\tat io.github.bonigarcia.wdm.WebDriverManager.handleException(WebDriverManager.java:1442)\n\tat io.github.bonigarcia.wdm.WebDriverManager.manage(WebDriverManager.java:1205)\n\tat io.github.bonigarcia.wdm.WebDriverManager.handleException(WebDriverManager.java:1435)\n\tat io.github.bonigarcia.wdm.WebDriverManager.manage(WebDriverManager.java:1205)\n\tat io.github.bonigarcia.wdm.WebDriverManager.setup(WebDriverManager.java:427)\n\tat helper.Utility.startDriver(Utility.java:47)\n\tat stepDef.Hooks.beforeTest(Hooks.java:30)\nCaused by: java.lang.NumberFormatException: For input string: \"public\"\n\tat java.base/java.lang.NumberFormatException.forInputString(NumberFormatException.java:67)\n\tat java.base/java.lang.Integer.parseInt(Integer.java:662)\n\tat java.base/java.lang.Integer.parseInt(Integer.java:778)\n\tat io.github.bonigarcia.wdm.managers.ChromeDriverManager.buildUrl(ChromeDriverManager.java:178)\n\tat io.github.bonigarcia.wdm.managers.ChromeDriverManager.buildUrl(ChromeDriverManager.java:155)\n\tat io.github.bonigarcia.wdm.WebDriverManager.download(WebDriverManager.java:1282)\n\tat io.github.bonigarcia.wdm.WebDriverManager.manage(WebDriverManager.java:1199)\n\tat io.github.bonigarcia.wdm.WebDriverManager.fallback(WebDriverManager.java:1461)\n\tat io.github.bonigarcia.wdm.WebDriverManager.handleException(WebDriverManager.java:1442)\n\tat io.github.bonigarcia.wdm.WebDriverManager.manage(WebDriverManager.java:1205)\n\tat io.github.bonigarcia.wdm.WebDriverManager.handleException(WebDriverManager.java:1435)\n\tat io.github.bonigarcia.wdm.WebDriverManager.manage(WebDriverManager.java:1205)\n\tat io.github.bonigarcia.wdm.WebDriverManager.setup(WebDriverManager.java:427)\n\tat helper.Utility.startDriver(Utility.java:47)\n\tat stepDef.Hooks.beforeTest(Hooks.java:30)\n\tat java.base/jdk.internal.reflect.DirectMethodHandleAccessor.invoke(DirectMethodHandleAccessor.java:103)\n\tat java.base/java.lang.reflect.Method.invoke(Method.java:580)\n\tat io.cucumber.java.Invoker.doInvoke(Invoker.java:66)\n\tat io.cucumber.java.Invoker.invoke(Invoker.java:24)\n\tat io.cucumber.java.AbstractGlueDefinition.invokeMethod(AbstractGlueDefinition.java:47)\n\tat io.cucumber.java.JavaHookDefinition.execute(JavaHookDefinition.java:64)\n\tat io.cucumber.core.runner.CoreHookDefinition.execute(CoreHookDefinition.java:46)\n\tat io.cucumber.core.runner.HookDefinitionMatch.runStep(HookDefinitionMatch.java:21)\n\tat io.cucumber.core.runner.ExecutionMode$1.execute(ExecutionMode.java:10)\n\tat io.cucumber.core.runner.TestStep.executeStep(TestStep.java:84)\n\tat io.cucumber.core.runner.TestStep.run(TestStep.java:56)\n\tat io.cucumber.core.runner.TestCase.run(TestCase.java:78)\n\tat io.cucumber.core.runner.Runner.runPickle(Runner.java:75)\n\tat io.cucumber.core.runtime.Runtime.lambda$executePickle$6(Runtime.java:107)\n\tat io.cucumber.core.runtime.CucumberExecutionContext.lambda$runTestCase$5(CucumberExecutionContext.java:137)\n\tat io.cucumber.core.runtime.RethrowingThrowableCollector.executeAndThrow(RethrowingThrowableCollector.java:23)\n\tat io.cucumber.core.runtime.CucumberExecutionContext.runTestCase(CucumberExecutionContext.java:137)\n\tat io.cucumber.core.runtime.Runtime.lambda$executePickle$7(Runtime.java:107)\n\tat java.base/java.util.concurrent.Executors$RunnableAdapter.call(Executors.java:572)\n\tat java.base/java.util.concurrent.FutureTask.run(FutureTask.java:317)\n\tat io.cucumber.core.runtime.Runtime$SameThreadExecutorService.execute(Runtime.java:235)\n\tat java.base/java.util.concurrent.AbstractExecutorService.submit(AbstractExecutorService.java:123)\n\tat io.cucumber.core.runtime.Runtime.lambda$runFeatures$3(Runtime.java:89)\n\tat java.base/java.util.stream.ReferencePipeline$3$1.accept(ReferencePipeline.java:197)\n\tat java.base/java.util.stream.SliceOps$1$1.accept(SliceOps.java:200)\n\tat java.base/java.util.ArrayList$ArrayListSpliterator.tryAdvance(ArrayList.java:1685)\n\tat java.base/java.util.stream.ReferencePipeline.forEachWithCancel(ReferencePipeline.java:129)\n\tat java.base/java.util.stream.AbstractPipeline.copyIntoWithCancel(AbstractPipeline.java:527)\n\tat java.base/java.util.stream.AbstractPipeline.copyInto(AbstractPipeline.java:513)\n\tat java.base/java.util.stream.AbstractPipeline.wrapAndCopyInto(AbstractPipeline.java:499)\n\tat java.base/java.util.stream.ReduceOps$ReduceOp.evaluateSequential(ReduceOps.java:921)\n\tat java.base/java.util.stream.AbstractPipeline.evaluate(AbstractPipeline.java:234)\n\tat java.base/java.util.stream.ReferencePipeline.collect(ReferencePipeline.java:682)\n\tat io.cucumber.core.runtime.Runtime.runFeatures(Runtime.java:90)\n\tat io.cucumber.core.runtime.Runtime.lambda$run$0(Runtime.java:78)\n\tat io.cucumber.core.runtime.CucumberExecutionContext.lambda$runFeatures$6(CucumberExecutionContext.java:148)\n\tat io.cucumber.core.runtime.CucumberExecutionContext.execute(CucumberExecutionContext.java:163)\n\tat io.cucumber.core.runtime.CucumberExecutionContext.runFeatures(CucumberExecutionContext.java:146)\n\tat io.cucumber.core.runtime.Runtime.run(Runtime.java:78)\n\tat io.cucumber.core.cli.Main.run(Main.java:87)\n\tat io.cucumber.core.cli.Main.main(Main.java:30)\n","duration":270910711,"status":"failed"},"match":{"location":"stepDef.Hooks.beforeTest(io.cucumber.java.Scenario)"}}],"line":42,"name":"Test logout normal","description":"","id":"test-automation-web;test-logout-normal","after":[{"result":{"error_message":"java.lang.NullPointerException: Cannot invoke \"org.openqa.selenium.WebDriver.quit()\" because \"helper.Utility.driver\" is null\n\tat helper.Utility.quitDriver(Utility.java:56)\n\tat stepDef.Hooks.afterTest(Hooks.java:39)\n","duration":2000534519,"status":"failed"},"match":{"location":"stepDef.Hooks.afterTest(io.cucumber.java.Scenario)"}}],"type":"scenario","keyword":"Scenario","steps":[{"result":{"duration":50214,"status":"skipped"},"line":43,"name":"user go to web page","match":{"location":"stepDef.WebStep.userGoToWebPage()"},"keyword":"Given "},{"result":{"duration":34734,"status":"skipped"},"line":44,"name":"user click sign up menu","match":{"location":"stepDef.WebStep.userClickSignUpMenu()"},"keyword":"And "},{"result":{"duration":40254,"status":"skipped"},"line":45,"name":"user input sign up username","match":{"location":"stepDef.WebStep.userInputSignUpUsername()"},"keyword":"And "},{"result":{"duration":50033,"status":"skipped"},"line":46,"name":"user input sign up pwd","match":{"location":"stepDef.WebStep.userInputSignUpPwd()"},"keyword":"And "},{"result":{"duration":56114,"status":"skipped"},"line":47,"name":"user click sign up button","match":{"location":"stepDef.WebStep.userClickSignUpButton()"},"keyword":"When "},{"result":{"duration":60112,"status":"skipped"},"line":48,"name":"validation get \"alert\" message \"Sign up successful.\"","match":{"arguments":[{"val":"\"alert\"","offset":15},{"val":"\"Sign up successful.\"","offset":31}],"location":"stepDef.WebStep.validationGetMessage(java.lang.String,java.lang.String)"},"keyword":"Then "},{"result":{"duration":52137,"status":"skipped"},"line":49,"name":"user click login menu","match":{"location":"stepDef.WebStep.userClickLoginMenu()"},"keyword":"And "},{"result":{"duration":45625,"status":"skipped"},"line":50,"name":"user input login username","match":{"location":"stepDef.WebStep.userInputLoginUsername()"},"keyword":"And "},{"result":{"duration":52157,"status":"skipped"},"line":51,"name":"user input login pwd","match":{"location":"stepDef.WebStep.userInputLoginPwd()"},"keyword":"And "},{"result":{"duration":53830,"status":"skipped"},"line":52,"name":"user click login button","match":{"location":"stepDef.WebStep.userClickLoginButton()"},"keyword":"When "},{"result":{"duration":54692,"status":"skipped"},"line":53,"name":"validation login successful","match":{"location":"stepDef.WebStep.validationLoginSuccessful()"},"keyword":"Then "},{"result":{"duration":88785,"status":"skipped"},"line":54,"name":"user click logout button","match":{"location":"stepDef.WebStep.userClickLogoutButton()"},"keyword":"And "},{"result":{"duration":53569,"status":"skipped"},"line":55,"name":"validation logout successful","match":{"location":"stepDef.WebStep.validationLogoutSuccessful()"},"keyword":"Then "}],"tags":[{"name":"@web"},{"name":"@web"}]},{"start_timestamp":"2024-02-22T17:45:30.104Z","before":[{"result":{"error_message":"io.github.bonigarcia.wdm.config.WebDriverManagerException: java.lang.NumberFormatException: For input string: \"public\"\n\tat io.github.bonigarcia.wdm.WebDriverManager.handleException(WebDriverManager.java:1445)\n\tat io.github.bonigarcia.wdm.WebDriverManager.manage(WebDriverManager.java:1205)\n\tat io.github.bonigarcia.wdm.WebDriverManager.fallback(WebDriverManager.java:1461)\n\tat io.github.bonigarcia.wdm.WebDriverManager.handleException(WebDriverManager.java:1442)\n\tat io.github.bonigarcia.wdm.WebDriverManager.manage(WebDriverManager.java:1205)\n\tat io.github.bonigarcia.wdm.WebDriverManager.handleException(WebDriverManager.java:1435)\n\tat io.github.bonigarcia.wdm.WebDriverManager.manage(WebDriverManager.java:1205)\n\tat io.github.bonigarcia.wdm.WebDriverManager.setup(WebDriverManager.java:427)\n\tat helper.Utility.startDriver(Utility.java:47)\n\tat stepDef.Hooks.beforeTest(Hooks.java:30)\nCaused by: java.lang.NumberFormatException: For input string: \"public\"\n\tat java.base/java.lang.NumberFormatException.forInputString(NumberFormatException.java:67)\n\tat java.base/java.lang.Integer.parseInt(Integer.java:662)\n\tat java.base/java.lang.Integer.parseInt(Integer.java:778)\n\tat io.github.bonigarcia.wdm.managers.ChromeDriverManager.buildUrl(ChromeDriverManager.java:178)\n\tat io.github.bonigarcia.wdm.managers.ChromeDriverManager.buildUrl(ChromeDriverManager.java:155)\n\tat io.github.bonigarcia.wdm.WebDriverManager.download(WebDriverManager.java:1282)\n\tat io.github.bonigarcia.wdm.WebDriverManager.manage(WebDriverManager.java:1199)\n\tat io.github.bonigarcia.wdm.WebDriverManager.fallback(WebDriverManager.java:1461)\n\tat io.github.bonigarcia.wdm.WebDriverManager.handleException(WebDriverManager.java:1442)\n\tat io.github.bonigarcia.wdm.WebDriverManager.manage(WebDriverManager.java:1205)\n\tat io.github.bonigarcia.wdm.WebDriverManager.handleException(WebDriverManager.java:1435)\n\tat io.github.bonigarcia.wdm.WebDriverManager.manage(WebDriverManager.java:1205)\n\tat io.github.bonigarcia.wdm.WebDriverManager.setup(WebDriverManager.java:427)\n\tat helper.Utility.startDriver(Utility.java:47)\n\tat stepDef.Hooks.beforeTest(Hooks.java:30)\n\tat java.base/jdk.internal.reflect.DirectMethodHandleAccessor.invoke(DirectMethodHandleAccessor.java:103)\n\tat java.base/java.lang.reflect.Method.invoke(Method.java:580)\n\tat io.cucumber.java.Invoker.doInvoke(Invoker.java:66)\n\tat io.cucumber.java.Invoker.invoke(Invoker.java:24)\n\tat io.cucumber.java.AbstractGlueDefinition.invokeMethod(AbstractGlueDefinition.java:47)\n\tat io.cucumber.java.JavaHookDefinition.execute(JavaHookDefinition.java:64)\n\tat io.cucumber.core.runner.CoreHookDefinition.execute(CoreHookDefinition.java:46)\n\tat io.cucumber.core.runner.HookDefinitionMatch.runStep(HookDefinitionMatch.java:21)\n\tat io.cucumber.core.runner.ExecutionMode$1.execute(ExecutionMode.java:10)\n\tat io.cucumber.core.runner.TestStep.executeStep(TestStep.java:84)\n\tat io.cucumber.core.runner.TestStep.run(TestStep.java:56)\n\tat io.cucumber.core.runner.TestCase.run(TestCase.java:78)\n\tat io.cucumber.core.runner.Runner.runPickle(Runner.java:75)\n\tat io.cucumber.core.runtime.Runtime.lambda$executePickle$6(Runtime.java:107)\n\tat io.cucumber.core.runtime.CucumberExecutionContext.lambda$runTestCase$5(CucumberExecutionContext.java:137)\n\tat io.cucumber.core.runtime.RethrowingThrowableCollector.executeAndThrow(RethrowingThrowableCollector.java:23)\n\tat io.cucumber.core.runtime.CucumberExecutionContext.runTestCase(CucumberExecutionContext.java:137)\n\tat io.cucumber.core.runtime.Runtime.lambda$executePickle$7(Runtime.java:107)\n\tat java.base/java.util.concurrent.Executors$RunnableAdapter.call(Executors.java:572)\n\tat java.base/java.util.concurrent.FutureTask.run(FutureTask.java:317)\n\tat io.cucumber.core.runtime.Runtime$SameThreadExecutorService.execute(Runtime.java:235)\n\tat java.base/java.util.concurrent.AbstractExecutorService.submit(AbstractExecutorService.java:123)\n\tat io.cucumber.core.runtime.Runtime.lambda$runFeatures$3(Runtime.java:89)\n\tat java.base/java.util.stream.ReferencePipeline$3$1.accept(ReferencePipeline.java:197)\n\tat java.base/java.util.stream.SliceOps$1$1.accept(SliceOps.java:200)\n\tat java.base/java.util.ArrayList$ArrayListSpliterator.tryAdvance(ArrayList.java:1685)\n\tat java.base/java.util.stream.ReferencePipeline.forEachWithCancel(ReferencePipeline.java:129)\n\tat java.base/java.util.stream.AbstractPipeline.copyIntoWithCancel(AbstractPipeline.java:527)\n\tat java.base/java.util.stream.AbstractPipeline.copyInto(AbstractPipeline.java:513)\n\tat java.base/java.util.stream.AbstractPipeline.wrapAndCopyInto(AbstractPipeline.java:499)\n\tat java.base/java.util.stream.ReduceOps$ReduceOp.evaluateSequential(ReduceOps.java:921)\n\tat java.base/java.util.stream.AbstractPipeline.evaluate(AbstractPipeline.java:234)\n\tat java.base/java.util.stream.ReferencePipeline.collect(ReferencePipeline.java:682)\n\tat io.cucumber.core.runtime.Runtime.runFeatures(Runtime.java:90)\n\tat io.cucumber.core.runtime.Runtime.lambda$run$0(Runtime.java:78)\n\tat io.cucumber.core.runtime.CucumberExecutionContext.lambda$runFeatures$6(CucumberExecutionContext.java:148)\n\tat io.cucumber.core.runtime.CucumberExecutionContext.execute(CucumberExecutionContext.java:163)\n\tat io.cucumber.core.runtime.CucumberExecutionContext.runFeatures(CucumberExecutionContext.java:146)\n\tat io.cucumber.core.runtime.Runtime.run(Runtime.java:78)\n\tat io.cucumber.core.cli.Main.run(Main.java:87)\n\tat io.cucumber.core.cli.Main.main(Main.java:30)\n","duration":703327086,"status":"failed"},"match":{"location":"stepDef.Hooks.beforeTest(io.cucumber.java.Scenario)"}}],"line":58,"name":"Test sort by product categories normal","description":"","id":"test-automation-web;test-sort-by-product-categories-normal","after":[{"result":{"error_message":"java.lang.NullPointerException: Cannot invoke \"org.openqa.selenium.WebDriver.quit()\" because \"helper.Utility.driver\" is null\n\tat helper.Utility.quitDriver(Utility.java:56)\n\tat stepDef.Hooks.afterTest(Hooks.java:39)\n","duration":2000620449,"status":"failed"},"match":{"location":"stepDef.Hooks.afterTest(io.cucumber.java.Scenario)"}}],"type":"scenario","keyword":"Scenario","steps":[{"result":{"duration":73457,"status":"skipped"},"line":59,"name":"user go to web page","match":{"location":"stepDef.WebStep.userGoToWebPage()"},"keyword":"Given "},{"result":{"duration":47768,"status":"skipped"},"line":60,"name":"user click sign up menu","match":{"location":"stepDef.WebStep.userClickSignUpMenu()"},"keyword":"And "},{"result":{"duration":48330,"status":"skipped"},"line":61,"name":"user input sign up username","match":{"location":"stepDef.WebStep.userInputSignUpUsername()"},"keyword":"And "},{"result":{"duration":51095,"status":"skipped"},"line":62,"name":"user input sign up pwd","match":{"location":"stepDef.WebStep.userInputSignUpPwd()"},"keyword":"And "},{"result":{"duration":50333,"status":"skipped"},"line":63,"name":"user click sign up button","match":{"location":"stepDef.WebStep.userClickSignUpButton()"},"keyword":"When "},{"result":{"duration":47528,"status":"skipped"},"line":64,"name":"validation get \"alert\" message \"Sign up successful.\"","match":{"arguments":[{"val":"\"alert\"","offset":15},{"val":"\"Sign up successful.\"","offset":31}],"location":"stepDef.WebStep.validationGetMessage(java.lang.String,java.lang.String)"},"keyword":"Then "},{"result":{"duration":48030,"status":"skipped"},"line":65,"name":"user click login menu","match":{"location":"stepDef.WebStep.userClickLoginMenu()"},"keyword":"And "},{"result":{"duration":47929,"status":"skipped"},"line":66,"name":"user input login username","match":{"location":"stepDef.WebStep.userInputLoginUsername()"},"keyword":"And "},{"result":{"duration":56114,"status":"skipped"},"line":67,"name":"user input login pwd","match":{"location":"stepDef.WebStep.userInputLoginPwd()"},"keyword":"And "},{"result":{"duration":56024,"status":"skipped"},"line":68,"name":"user click login button","match":{"location":"stepDef.WebStep.userClickLoginButton()"},"keyword":"When "},{"result":{"duration":50745,"status":"skipped"},"line":69,"name":"validation login successful","match":{"location":"stepDef.WebStep.validationLoginSuccessful()"},"keyword":"Then "},{"result":{"duration":48330,"status":"skipped"},"line":70,"name":"user click categories \"Phones\"","match":{"arguments":[{"val":"\"Phones\"","offset":22}],"location":"stepDef.WebStep.userClickCategories(java.lang.String)"},"keyword":"And "},{"result":{"duration":52928,"status":"skipped"},"line":71,"name":"validation page display \"Phones\" product","match":{"arguments":[{"val":"\"Phones\"","offset":24}],"location":"stepDef.WebStep.validationPageDisplayProduct(java.lang.String)"},"keyword":"Then "},{"result":{"duration":49061,"status":"skipped"},"line":72,"name":"user click categories \"Laptops\"","match":{"arguments":[{"val":"\"Laptops\"","offset":22}],"location":"stepDef.WebStep.userClickCategories(java.lang.String)"},"keyword":"And "},{"result":{"duration":52688,"status":"skipped"},"line":73,"name":"validation page display \"Laptops\" product","match":{"arguments":[{"val":"\"Laptops\"","offset":24}],"location":"stepDef.WebStep.validationPageDisplayProduct(java.lang.String)"},"keyword":"Then "},{"result":{"duration":53059,"status":"skipped"},"line":74,"name":"user click categories \"Monitors\"","match":{"arguments":[{"val":"\"Monitors\"","offset":22}],"location":"stepDef.WebStep.userClickCategories(java.lang.String)"},"keyword":"And "},{"result":{"duration":51226,"status":"skipped"},"line":75,"name":"validation page display \"Monitors\" product","match":{"arguments":[{"val":"\"Monitors\"","offset":24}],"location":"stepDef.WebStep.validationPageDisplayProduct(java.lang.String)"},"keyword":"Then "}],"tags":[{"name":"@web"},{"name":"@web"}]},{"start_timestamp":"2024-02-22T17:45:32.819Z","before":[{"result":{"error_message":"io.github.bonigarcia.wdm.config.WebDriverManagerException: java.lang.NumberFormatException: For input string: \"public\"\n\tat io.github.bonigarcia.wdm.WebDriverManager.handleException(WebDriverManager.java:1445)\n\tat io.github.bonigarcia.wdm.WebDriverManager.manage(WebDriverManager.java:1205)\n\tat io.github.bonigarcia.wdm.WebDriverManager.fallback(WebDriverManager.java:1461)\n\tat io.github.bonigarcia.wdm.WebDriverManager.handleException(WebDriverManager.java:1442)\n\tat io.github.bonigarcia.wdm.WebDriverManager.manage(WebDriverManager.java:1205)\n\tat io.github.bonigarcia.wdm.WebDriverManager.handleException(WebDriverManager.java:1435)\n\tat io.github.bonigarcia.wdm.WebDriverManager.manage(WebDriverManager.java:1205)\n\tat io.github.bonigarcia.wdm.WebDriverManager.setup(WebDriverManager.java:427)\n\tat helper.Utility.startDriver(Utility.java:47)\n\tat stepDef.Hooks.beforeTest(Hooks.java:30)\nCaused by: java.lang.NumberFormatException: For input string: \"public\"\n\tat java.base/java.lang.NumberFormatException.forInputString(NumberFormatException.java:67)\n\tat java.base/java.lang.Integer.parseInt(Integer.java:662)\n\tat java.base/java.lang.Integer.parseInt(Integer.java:778)\n\tat io.github.bonigarcia.wdm.managers.ChromeDriverManager.buildUrl(ChromeDriverManager.java:178)\n\tat io.github.bonigarcia.wdm.managers.ChromeDriverManager.buildUrl(ChromeDriverManager.java:155)\n\tat io.github.bonigarcia.wdm.WebDriverManager.download(WebDriverManager.java:1282)\n\tat io.github.bonigarcia.wdm.WebDriverManager.manage(WebDriverManager.java:1199)\n\tat io.github.bonigarcia.wdm.WebDriverManager.fallback(WebDriverManager.java:1461)\n\tat io.github.bonigarcia.wdm.WebDriverManager.handleException(WebDriverManager.java:1442)\n\tat io.github.bonigarcia.wdm.WebDriverManager.manage(WebDriverManager.java:1205)\n\tat io.github.bonigarcia.wdm.WebDriverManager.handleException(WebDriverManager.java:1435)\n\tat io.github.bonigarcia.wdm.WebDriverManager.manage(WebDriverManager.java:1205)\n\tat io.github.bonigarcia.wdm.WebDriverManager.setup(WebDriverManager.java:427)\n\tat helper.Utility.startDriver(Utility.java:47)\n\tat stepDef.Hooks.beforeTest(Hooks.java:30)\n\tat java.base/jdk.internal.reflect.DirectMethodHandleAccessor.invoke(DirectMethodHandleAccessor.java:103)\n\tat java.base/java.lang.reflect.Method.invoke(Method.java:580)\n\tat io.cucumber.java.Invoker.doInvoke(Invoker.java:66)\n\tat io.cucumber.java.Invoker.invoke(Invoker.java:24)\n\tat io.cucumber.java.AbstractGlueDefinition.invokeMethod(AbstractGlueDefinition.java:47)\n\tat io.cucumber.java.JavaHookDefinition.execute(JavaHookDefinition.java:64)\n\tat io.cucumber.core.runner.CoreHookDefinition.execute(CoreHookDefinition.java:46)\n\tat io.cucumber.core.runner.HookDefinitionMatch.runStep(HookDefinitionMatch.java:21)\n\tat io.cucumber.core.runner.ExecutionMode$1.execute(ExecutionMode.java:10)\n\tat io.cucumber.core.runner.TestStep.executeStep(TestStep.java:84)\n\tat io.cucumber.core.runner.TestStep.run(TestStep.java:56)\n\tat io.cucumber.core.runner.TestCase.run(TestCase.java:78)\n\tat io.cucumber.core.runner.Runner.runPickle(Runner.java:75)\n\tat io.cucumber.core.runtime.Runtime.lambda$executePickle$6(Runtime.java:107)\n\tat io.cucumber.core.runtime.CucumberExecutionContext.lambda$runTestCase$5(CucumberExecutionContext.java:137)\n\tat io.cucumber.core.runtime.RethrowingThrowableCollector.executeAndThrow(RethrowingThrowableCollector.java:23)\n\tat io.cucumber.core.runtime.CucumberExecutionContext.runTestCase(CucumberExecutionContext.java:137)\n\tat io.cucumber.core.runtime.Runtime.lambda$executePickle$7(Runtime.java:107)\n\tat java.base/java.util.concurrent.Executors$RunnableAdapter.call(Executors.java:572)\n\tat java.base/java.util.concurrent.FutureTask.run(FutureTask.java:317)\n\tat io.cucumber.core.runtime.Runtime$SameThreadExecutorService.execute(Runtime.java:235)\n\tat java.base/java.util.concurrent.AbstractExecutorService.submit(AbstractExecutorService.java:123)\n\tat io.cucumber.core.runtime.Runtime.lambda$runFeatures$3(Runtime.java:89)\n\tat java.base/java.util.stream.ReferencePipeline$3$1.accept(ReferencePipeline.java:197)\n\tat java.base/java.util.stream.SliceOps$1$1.accept(SliceOps.java:200)\n\tat java.base/java.util.ArrayList$ArrayListSpliterator.tryAdvance(ArrayList.java:1685)\n\tat java.base/java.util.stream.ReferencePipeline.forEachWithCancel(ReferencePipeline.java:129)\n\tat java.base/java.util.stream.AbstractPipeline.copyIntoWithCancel(AbstractPipeline.java:527)\n\tat java.base/java.util.stream.AbstractPipeline.copyInto(AbstractPipeline.java:513)\n\tat java.base/java.util.stream.AbstractPipeline.wrapAndCopyInto(AbstractPipeline.java:499)\n\tat java.base/java.util.stream.ReduceOps$ReduceOp.evaluateSequential(ReduceOps.java:921)\n\tat java.base/java.util.stream.AbstractPipeline.evaluate(AbstractPipeline.java:234)\n\tat java.base/java.util.stream.ReferencePipeline.collect(ReferencePipeline.java:682)\n\tat io.cucumber.core.runtime.Runtime.runFeatures(Runtime.java:90)\n\tat io.cucumber.core.runtime.Runtime.lambda$run$0(Runtime.java:78)\n\tat io.cucumber.core.runtime.CucumberExecutionContext.lambda$runFeatures$6(CucumberExecutionContext.java:148)\n\tat io.cucumber.core.runtime.CucumberExecutionContext.execute(CucumberExecutionContext.java:163)\n\tat io.cucumber.core.runtime.CucumberExecutionContext.runFeatures(CucumberExecutionContext.java:146)\n\tat io.cucumber.core.runtime.Runtime.run(Runtime.java:78)\n\tat io.cucumber.core.cli.Main.run(Main.java:87)\n\tat io.cucumber.core.cli.Main.main(Main.java:30)\n","duration":552101958,"status":"failed"},"match":{"location":"stepDef.Hooks.beforeTest(io.cucumber.java.Scenario)"}}],"line":78,"name":"Test add to cart normal","description":"","id":"test-automation-web;test-add-to-cart-normal","after":[{"result":{"error_message":"java.lang.NullPointerException: Cannot invoke \"org.openqa.selenium.WebDriver.quit()\" because \"helper.Utility.driver\" is null\n\tat helper.Utility.quitDriver(Utility.java:56)\n\tat stepDef.Hooks.afterTest(Hooks.java:39)\n","duration":2000516594,"status":"failed"},"match":{"location":"stepDef.Hooks.afterTest(io.cucumber.java.Scenario)"}}],"type":"scenario","keyword":"Scenario","steps":[{"result":{"duration":120644,"status":"skipped"},"line":79,"name":"user go to web page","match":{"location":"stepDef.WebStep.userGoToWebPage()"},"keyword":"Given "},{"result":{"duration":48510,"status":"skipped"},"line":80,"name":"user click sign up menu","match":{"location":"stepDef.WebStep.userClickSignUpMenu()"},"keyword":"And "},{"result":{"duration":47859,"status":"skipped"},"line":81,"name":"user input sign up username","match":{"location":"stepDef.WebStep.userInputSignUpUsername()"},"keyword":"And "},{"result":{"duration":50143,"status":"skipped"},"line":82,"name":"user input sign up pwd","match":{"location":"stepDef.WebStep.userInputSignUpPwd()"},"keyword":"And "},{"result":{"duration":46777,"status":"skipped"},"line":83,"name":"user click sign up button","match":{"location":"stepDef.WebStep.userClickSignUpButton()"},"keyword":"When "},{"result":{"duration":51887,"status":"skipped"},"line":84,"name":"validation get \"alert\" message \"Sign up successful.\"","match":{"arguments":[{"val":"\"alert\"","offset":15},{"val":"\"Sign up successful.\"","offset":31}],"location":"stepDef.WebStep.validationGetMessage(java.lang.String,java.lang.String)"},"keyword":"Then "},{"result":{"duration":52658,"status":"skipped"},"line":85,"name":"user click login menu","match":{"location":"stepDef.WebStep.userClickLoginMenu()"},"keyword":"And "},{"result":{"duration":63297,"status":"skipped"},"line":86,"name":"user input login username","match":{"location":"stepDef.WebStep.userInputLoginUsername()"},"keyword":"And "},{"result":{"duration":31509,"status":"skipped"},"line":87,"name":"user input login pwd","match":{"location":"stepDef.WebStep.userInputLoginPwd()"},"keyword":"And "},{"result":{"duration":29996,"status":"skipped"},"line":88,"name":"user click login button","match":{"location":"stepDef.WebStep.userClickLoginButton()"},"keyword":"When "},{"result":{"duration":39945,"status":"skipped"},"line":89,"name":"validation login successful","match":{"location":"stepDef.WebStep.validationLoginSuccessful()"},"keyword":"Then "},{"result":{"duration":30487,"status":"skipped"},"line":90,"name":"user click product name","match":{"location":"stepDef.WebStep.userClickProductName()"},"keyword":"And "},{"result":{"duration":45124,"status":"skipped"},"line":91,"name":"user click add to cart button","match":{"location":"stepDef.WebStep.userClickAddToCartButton()"},"keyword":"And "},{"result":{"duration":32591,"status":"skipped"},"line":92,"name":"validation get \"alert\" message \"Product added.\"","match":{"arguments":[{"val":"\"alert\"","offset":15},{"val":"\"Product added.\"","offset":31}],"location":"stepDef.WebStep.validationGetMessage(java.lang.String,java.lang.String)"},"keyword":"Then "},{"result":{"duration":30266,"status":"skipped"},"line":93,"name":"user click home menu","match":{"location":"stepDef.WebStep.userClickHomeMenu()"},"keyword":"And "},{"result":{"duration":28984,"status":"skipped"},"line":94,"name":"user click product name","match":{"location":"stepDef.WebStep.userClickProductName()"},"keyword":"And "},{"result":{"duration":29665,"status":"skipped"},"line":95,"name":"user click add to cart button","match":{"location":"stepDef.WebStep.userClickAddToCartButton()"},"keyword":"And "},{"result":{"duration":28783,"status":"skipped"},"line":96,"name":"validation get \"alert\" message \"Product added.\"","match":{"arguments":[{"val":"\"alert\"","offset":15},{"val":"\"Product added.\"","offset":31}],"location":"stepDef.WebStep.validationGetMessage(java.lang.String,java.lang.String)"},"keyword":"Then "},{"result":{"duration":32160,"status":"skipped"},"line":97,"name":"user click cart menu","match":{"location":"stepDef.WebStep.userClickCartMenu()"},"keyword":"And "},{"result":{"duration":40996,"status":"skipped"},"line":98,"name":"validation cart page display equals 2 product","match":{"arguments":[{"val":"2","offset":36}],"location":"stepDef.WebStep.validationCartPageDisplayEqualsProduct(int)"},"keyword":"Then "},{"result":{"duration":29546,"status":"skipped"},"line":99,"name":"validation total price is equals price of product","match":{"location":"stepDef.WebStep.validationTotalPriceIsEqualsPriceOfProduct()"},"keyword":"Then "}],"tags":[{"name":"@web"},{"name":"@web"}]},{"start_timestamp":"2024-02-22T17:45:35.383Z","before":[{"result":{"error_message":"io.github.bonigarcia.wdm.config.WebDriverManagerException: java.lang.NumberFormatException: For input string: \"public\"\n\tat io.github.bonigarcia.wdm.WebDriverManager.handleException(WebDriverManager.java:1445)\n\tat io.github.bonigarcia.wdm.WebDriverManager.manage(WebDriverManager.java:1205)\n\tat io.github.bonigarcia.wdm.WebDriverManager.fallback(WebDriverManager.java:1461)\n\tat io.github.bonigarcia.wdm.WebDriverManager.handleException(WebDriverManager.java:1442)\n\tat io.github.bonigarcia.wdm.WebDriverManager.manage(WebDriverManager.java:1205)\n\tat io.github.bonigarcia.wdm.WebDriverManager.handleException(WebDriverManager.java:1435)\n\tat io.github.bonigarcia.wdm.WebDriverManager.manage(WebDriverManager.java:1205)\n\tat io.github.bonigarcia.wdm.WebDriverManager.setup(WebDriverManager.java:427)\n\tat helper.Utility.startDriver(Utility.java:47)\n\tat stepDef.Hooks.beforeTest(Hooks.java:30)\nCaused by: java.lang.NumberFormatException: For input string: \"public\"\n\tat java.base/java.lang.NumberFormatException.forInputString(NumberFormatException.java:67)\n\tat java.base/java.lang.Integer.parseInt(Integer.java:662)\n\tat java.base/java.lang.Integer.parseInt(Integer.java:778)\n\tat io.github.bonigarcia.wdm.managers.ChromeDriverManager.buildUrl(ChromeDriverManager.java:178)\n\tat io.github.bonigarcia.wdm.managers.ChromeDriverManager.buildUrl(ChromeDriverManager.java:155)\n\tat io.github.bonigarcia.wdm.WebDriverManager.download(WebDriverManager.java:1282)\n\tat io.github.bonigarcia.wdm.WebDriverManager.manage(WebDriverManager.java:1199)\n\tat io.github.bonigarcia.wdm.WebDriverManager.fallback(WebDriverManager.java:1461)\n\tat io.github.bonigarcia.wdm.WebDriverManager.handleException(WebDriverManager.java:1442)\n\tat io.github.bonigarcia.wdm.WebDriverManager.manage(WebDriverManager.java:1205)\n\tat io.github.bonigarcia.wdm.WebDriverManager.handleException(WebDriverManager.java:1435)\n\tat io.github.bonigarcia.wdm.WebDriverManager.manage(WebDriverManager.java:1205)\n\tat io.github.bonigarcia.wdm.WebDriverManager.setup(WebDriverManager.java:427)\n\tat helper.Utility.startDriver(Utility.java:47)\n\tat stepDef.Hooks.beforeTest(Hooks.java:30)\n\tat java.base/jdk.internal.reflect.DirectMethodHandleAccessor.invoke(DirectMethodHandleAccessor.java:103)\n\tat java.base/java.lang.reflect.Method.invoke(Method.java:580)\n\tat io.cucumber.java.Invoker.doInvoke(Invoker.java:66)\n\tat io.cucumber.java.Invoker.invoke(Invoker.java:24)\n\tat io.cucumber.java.AbstractGlueDefinition.invokeMethod(AbstractGlueDefinition.java:47)\n\tat io.cucumber.java.JavaHookDefinition.execute(JavaHookDefinition.java:64)\n\tat io.cucumber.core.runner.CoreHookDefinition.execute(CoreHookDefinition.java:46)\n\tat io.cucumber.core.runner.HookDefinitionMatch.runStep(HookDefinitionMatch.java:21)\n\tat io.cucumber.core.runner.ExecutionMode$1.execute(ExecutionMode.java:10)\n\tat io.cucumber.core.runner.TestStep.executeStep(TestStep.java:84)\n\tat io.cucumber.core.runner.TestStep.run(TestStep.java:56)\n\tat io.cucumber.core.runner.TestCase.run(TestCase.java:78)\n\tat io.cucumber.core.runner.Runner.runPickle(Runner.java:75)\n\tat io.cucumber.core.runtime.Runtime.lambda$executePickle$6(Runtime.java:107)\n\tat io.cucumber.core.runtime.CucumberExecutionContext.lambda$runTestCase$5(CucumberExecutionContext.java:137)\n\tat io.cucumber.core.runtime.RethrowingThrowableCollector.executeAndThrow(RethrowingThrowableCollector.java:23)\n\tat io.cucumber.core.runtime.CucumberExecutionContext.runTestCase(CucumberExecutionContext.java:137)\n\tat io.cucumber.core.runtime.Runtime.lambda$executePickle$7(Runtime.java:107)\n\tat java.base/java.util.concurrent.Executors$RunnableAdapter.call(Executors.java:572)\n\tat java.base/java.util.concurrent.FutureTask.run(FutureTask.java:317)\n\tat io.cucumber.core.runtime.Runtime$SameThreadExecutorService.execute(Runtime.java:235)\n\tat java.base/java.util.concurrent.AbstractExecutorService.submit(AbstractExecutorService.java:123)\n\tat io.cucumber.core.runtime.Runtime.lambda$runFeatures$3(Runtime.java:89)\n\tat java.base/java.util.stream.ReferencePipeline$3$1.accept(ReferencePipeline.java:197)\n\tat java.base/java.util.stream.SliceOps$1$1.accept(SliceOps.java:200)\n\tat java.base/java.util.ArrayList$ArrayListSpliterator.tryAdvance(ArrayList.java:1685)\n\tat java.base/java.util.stream.ReferencePipeline.forEachWithCancel(ReferencePipeline.java:129)\n\tat java.base/java.util.stream.AbstractPipeline.copyIntoWithCancel(AbstractPipeline.java:527)\n\tat java.base/java.util.stream.AbstractPipeline.copyInto(AbstractPipeline.java:513)\n\tat java.base/java.util.stream.AbstractPipeline.wrapAndCopyInto(AbstractPipeline.java:499)\n\tat java.base/java.util.stream.ReduceOps$ReduceOp.evaluateSequential(ReduceOps.java:921)\n\tat java.base/java.util.stream.AbstractPipeline.evaluate(AbstractPipeline.java:234)\n\tat java.base/java.util.stream.ReferencePipeline.collect(ReferencePipeline.java:682)\n\tat io.cucumber.core.runtime.Runtime.runFeatures(Runtime.java:90)\n\tat io.cucumber.core.runtime.Runtime.lambda$run$0(Runtime.java:78)\n\tat io.cucumber.core.runtime.CucumberExecutionContext.lambda$runFeatures$6(CucumberExecutionContext.java:148)\n\tat io.cucumber.core.runtime.CucumberExecutionContext.execute(CucumberExecutionContext.java:163)\n\tat io.cucumber.core.runtime.CucumberExecutionContext.runFeatures(CucumberExecutionContext.java:146)\n\tat io.cucumber.core.runtime.Runtime.run(Runtime.java:78)\n\tat io.cucumber.core.cli.Main.run(Main.java:87)\n\tat io.cucumber.core.cli.Main.main(Main.java:30)\n","duration":504387470,"status":"failed"},"match":{"location":"stepDef.Hooks.beforeTest(io.cucumber.java.Scenario)"}}],"line":102,"name":"Test delete product from cart","description":"","id":"test-automation-web;test-delete-product-from-cart","after":[{"result":{"error_message":"java.lang.NullPointerException: Cannot invoke \"org.openqa.selenium.WebDriver.quit()\" because \"helper.Utility.driver\" is null\n\tat helper.Utility.quitDriver(Utility.java:56)\n\tat stepDef.Hooks.afterTest(Hooks.java:39)\n","duration":2000523899,"status":"failed"},"match":{"location":"stepDef.Hooks.afterTest(io.cucumber.java.Scenario)"}}],"type":"scenario","keyword":"Scenario","steps":[{"result":{"duration":62236,"status":"skipped"},"line":103,"name":"user go to web page","match":{"location":"stepDef.WebStep.userGoToWebPage()"},"keyword":"Given "},{"result":{"duration":46517,"status":"skipped"},"line":104,"name":"user click sign up menu","match":{"location":"stepDef.WebStep.userClickSignUpMenu()"},"keyword":"And "},{"result":{"duration":59421,"status":"skipped"},"line":105,"name":"user input sign up username","match":{"location":"stepDef.WebStep.userInputSignUpUsername()"},"keyword":"And "},{"result":{"duration":44072,"status":"skipped"},"line":106,"name":"user input sign up pwd","match":{"location":"stepDef.WebStep.userInputSignUpPwd()"},"keyword":"And "},{"result":{"duration":46646,"status":"skipped"},"line":107,"name":"user click sign up button","match":{"location":"stepDef.WebStep.userClickSignUpButton()"},"keyword":"When "},{"result":{"duration":48690,"status":"skipped"},"line":108,"name":"validation get \"alert\" message \"Sign up successful.\"","match":{"arguments":[{"val":"\"alert\"","offset":15},{"val":"\"Sign up successful.\"","offset":31}],"location":"stepDef.WebStep.validationGetMessage(java.lang.String,java.lang.String)"},"keyword":"Then "},{"result":{"duration":45976,"status":"skipped"},"line":109,"name":"user click login menu","match":{"location":"stepDef.WebStep.userClickLoginMenu()"},"keyword":"And "},{"result":{"duration":51336,"status":"skipped"},"line":110,"name":"user input login username","match":{"location":"stepDef.WebStep.userInputLoginUsername()"},"keyword":"And "},{"result":{"duration":48200,"status":"skipped"},"line":111,"name":"user input login pwd","match":{"location":"stepDef.WebStep.userInputLoginPwd()"},"keyword":"And "},{"result":{"duration":41467,"status":"skipped"},"line":112,"name":"user click login button","match":{"location":"stepDef.WebStep.userClickLoginButton()"},"keyword":"When "},{"result":{"duration":41026,"status":"skipped"},"line":113,"name":"validation login successful","match":{"location":"stepDef.WebStep.validationLoginSuccessful()"},"keyword":"Then "},{"result":{"duration":39073,"status":"skipped"},"line":114,"name":"user click product name","match":{"location":"stepDef.WebStep.userClickProductName()"},"keyword":"And "},{"result":{"duration":39073,"status":"skipped"},"line":115,"name":"user click add to cart button","match":{"location":"stepDef.WebStep.userClickAddToCartButton()"},"keyword":"And "},{"result":{"duration":49162,"status":"skipped"},"line":116,"name":"validation get \"alert\" message \"Product added.\"","match":{"arguments":[{"val":"\"alert\"","offset":15},{"val":"\"Product added.\"","offset":31}],"location":"stepDef.WebStep.validationGetMessage(java.lang.String,java.lang.String)"},"keyword":"Then "},{"result":{"duration":37981,"status":"skipped"},"line":117,"name":"user click home menu","match":{"location":"stepDef.WebStep.userClickHomeMenu()"},"keyword":"And "},{"result":{"duration":40776,"status":"skipped"},"line":118,"name":"user click product name","match":{"location":"stepDef.WebStep.userClickProductName()"},"keyword":"And "},{"result":{"duration":36177,"status":"skipped"},"line":119,"name":"user click add to cart button","match":{"location":"stepDef.WebStep.userClickAddToCartButton()"},"keyword":"And "},{"result":{"duration":49152,"status":"skipped"},"line":120,"name":"validation get \"alert\" message \"Product added.\"","match":{"arguments":[{"val":"\"alert\"","offset":15},{"val":"\"Product added.\"","offset":31}],"location":"stepDef.WebStep.validationGetMessage(java.lang.String,java.lang.String)"},"keyword":"Then "},{"result":{"duration":35456,"status":"skipped"},"line":121,"name":"user click cart menu","match":{"location":"stepDef.WebStep.userClickCartMenu()"},"keyword":"And "},{"result":{"duration":33883,"status":"skipped"},"line":122,"name":"validation cart page display equals 2 product","match":{"arguments":[{"val":"2","offset":36}],"location":"stepDef.WebStep.validationCartPageDisplayEqualsProduct(int)"},"keyword":"Then "},{"result":{"duration":43591,"status":"skipped"},"line":123,"name":"validation total price is equals price of product","match":{"location":"stepDef.WebStep.validationTotalPriceIsEqualsPriceOfProduct()"},"keyword":"Then "},{"result":{"duration":36909,"status":"skipped"},"line":124,"name":"user click delete product from cart","match":{"location":"stepDef.WebStep.userClickDeleteProductFromCart()"},"keyword":"And "},{"result":{"duration":45425,"status":"skipped"},"line":125,"name":"validation cart page display equals 1 product","match":{"arguments":[{"val":"1","offset":36}],"location":"stepDef.WebStep.validationCartPageDisplayEqualsProduct(int)"},"keyword":"Then "},{"result":{"duration":41226,"status":"skipped"},"line":126,"name":"validation total price is equals price of product","match":{"location":"stepDef.WebStep.validationTotalPriceIsEqualsPriceOfProduct()"},"keyword":"Then "},{"result":{"duration":37079,"status":"skipped"},"line":127,"name":"user click delete product from cart","match":{"location":"stepDef.WebStep.userClickDeleteProductFromCart()"},"keyword":"And "},{"result":{"duration":52046,"status":"skipped"},"line":128,"name":"validation cart page display equals 0 product","match":{"arguments":[{"val":"0","offset":36}],"location":"stepDef.WebStep.validationCartPageDisplayEqualsProduct(int)"},"keyword":"Then "},{"result":{"duration":43320,"status":"skipped"},"line":129,"name":"validation total price is equals price of product","match":{"location":"stepDef.WebStep.validationTotalPriceIsEqualsPriceOfProduct()"},"keyword":"Then "}],"tags":[{"name":"@web"},{"name":"@web"}]},{"start_timestamp":"2024-02-22T17:45:37.901Z","before":[{"result":{"error_message":"io.github.bonigarcia.wdm.config.WebDriverManagerException: java.lang.NumberFormatException: For input string: \"public\"\n\tat io.github.bonigarcia.wdm.WebDriverManager.handleException(WebDriverManager.java:1445)\n\tat io.github.bonigarcia.wdm.WebDriverManager.manage(WebDriverManager.java:1205)\n\tat io.github.bonigarcia.wdm.WebDriverManager.fallback(WebDriverManager.java:1461)\n\tat io.github.bonigarcia.wdm.WebDriverManager.handleException(WebDriverManager.java:1442)\n\tat io.github.bonigarcia.wdm.WebDriverManager.manage(WebDriverManager.java:1205)\n\tat io.github.bonigarcia.wdm.WebDriverManager.handleException(WebDriverManager.java:1435)\n\tat io.github.bonigarcia.wdm.WebDriverManager.manage(WebDriverManager.java:1205)\n\tat io.github.bonigarcia.wdm.WebDriverManager.setup(WebDriverManager.java:427)\n\tat helper.Utility.startDriver(Utility.java:47)\n\tat stepDef.Hooks.beforeTest(Hooks.java:30)\nCaused by: java.lang.NumberFormatException: For input string: \"public\"\n\tat java.base/java.lang.NumberFormatException.forInputString(NumberFormatException.java:67)\n\tat java.base/java.lang.Integer.parseInt(Integer.java:662)\n\tat java.base/java.lang.Integer.parseInt(Integer.java:778)\n\tat io.github.bonigarcia.wdm.managers.ChromeDriverManager.buildUrl(ChromeDriverManager.java:178)\n\tat io.github.bonigarcia.wdm.managers.ChromeDriverManager.buildUrl(ChromeDriverManager.java:155)\n\tat io.github.bonigarcia.wdm.WebDriverManager.download(WebDriverManager.java:1282)\n\tat io.github.bonigarcia.wdm.WebDriverManager.manage(WebDriverManager.java:1199)\n\tat io.github.bonigarcia.wdm.WebDriverManager.fallback(WebDriverManager.java:1461)\n\tat io.github.bonigarcia.wdm.WebDriverManager.handleException(WebDriverManager.java:1442)\n\tat io.github.bonigarcia.wdm.WebDriverManager.manage(WebDriverManager.java:1205)\n\tat io.github.bonigarcia.wdm.WebDriverManager.handleException(WebDriverManager.java:1435)\n\tat io.github.bonigarcia.wdm.WebDriverManager.manage(WebDriverManager.java:1205)\n\tat io.github.bonigarcia.wdm.WebDriverManager.setup(WebDriverManager.java:427)\n\tat helper.Utility.startDriver(Utility.java:47)\n\tat stepDef.Hooks.beforeTest(Hooks.java:30)\n\tat java.base/jdk.internal.reflect.DirectMethodHandleAccessor.invoke(DirectMethodHandleAccessor.java:103)\n\tat java.base/java.lang.reflect.Method.invoke(Method.java:580)\n\tat io.cucumber.java.Invoker.doInvoke(Invoker.java:66)\n\tat io.cucumber.java.Invoker.invoke(Invoker.java:24)\n\tat io.cucumber.java.AbstractGlueDefinition.invokeMethod(AbstractGlueDefinition.java:47)\n\tat io.cucumber.java.JavaHookDefinition.execute(JavaHookDefinition.java:64)\n\tat io.cucumber.core.runner.CoreHookDefinition.execute(CoreHookDefinition.java:46)\n\tat io.cucumber.core.runner.HookDefinitionMatch.runStep(HookDefinitionMatch.java:21)\n\tat io.cucumber.core.runner.ExecutionMode$1.execute(ExecutionMode.java:10)\n\tat io.cucumber.core.runner.TestStep.executeStep(TestStep.java:84)\n\tat io.cucumber.core.runner.TestStep.run(TestStep.java:56)\n\tat io.cucumber.core.runner.TestCase.run(TestCase.java:78)\n\tat io.cucumber.core.runner.Runner.runPickle(Runner.java:75)\n\tat io.cucumber.core.runtime.Runtime.lambda$executePickle$6(Runtime.java:107)\n\tat io.cucumber.core.runtime.CucumberExecutionContext.lambda$runTestCase$5(CucumberExecutionContext.java:137)\n\tat io.cucumber.core.runtime.RethrowingThrowableCollector.executeAndThrow(RethrowingThrowableCollector.java:23)\n\tat io.cucumber.core.runtime.CucumberExecutionContext.runTestCase(CucumberExecutionContext.java:137)\n\tat io.cucumber.core.runtime.Runtime.lambda$executePickle$7(Runtime.java:107)\n\tat java.base/java.util.concurrent.Executors$RunnableAdapter.call(Executors.java:572)\n\tat java.base/java.util.concurrent.FutureTask.run(FutureTask.java:317)\n\tat io.cucumber.core.runtime.Runtime$SameThreadExecutorService.execute(Runtime.java:235)\n\tat java.base/java.util.concurrent.AbstractExecutorService.submit(AbstractExecutorService.java:123)\n\tat io.cucumber.core.runtime.Runtime.lambda$runFeatures$3(Runtime.java:89)\n\tat java.base/java.util.stream.ReferencePipeline$3$1.accept(ReferencePipeline.java:197)\n\tat java.base/java.util.stream.SliceOps$1$1.accept(SliceOps.java:200)\n\tat java.base/java.util.ArrayList$ArrayListSpliterator.tryAdvance(ArrayList.java:1685)\n\tat java.base/java.util.stream.ReferencePipeline.forEachWithCancel(ReferencePipeline.java:129)\n\tat java.base/java.util.stream.AbstractPipeline.copyIntoWithCancel(AbstractPipeline.java:527)\n\tat java.base/java.util.stream.AbstractPipeline.copyInto(AbstractPipeline.java:513)\n\tat java.base/java.util.stream.AbstractPipeline.wrapAndCopyInto(AbstractPipeline.java:499)\n\tat java.base/java.util.stream.ReduceOps$ReduceOp.evaluateSequential(ReduceOps.java:921)\n\tat java.base/java.util.stream.AbstractPipeline.evaluate(AbstractPipeline.java:234)\n\tat java.base/java.util.stream.ReferencePipeline.collect(ReferencePipeline.java:682)\n\tat io.cucumber.core.runtime.Runtime.runFeatures(Runtime.java:90)\n\tat io.cucumber.core.runtime.Runtime.lambda$run$0(Runtime.java:78)\n\tat io.cucumber.core.runtime.CucumberExecutionContext.lambda$runFeatures$6(CucumberExecutionContext.java:148)\n\tat io.cucumber.core.runtime.CucumberExecutionContext.execute(CucumberExecutionContext.java:163)\n\tat io.cucumber.core.runtime.CucumberExecutionContext.runFeatures(CucumberExecutionContext.java:146)\n\tat io.cucumber.core.runtime.Runtime.run(Runtime.java:78)\n\tat io.cucumber.core.cli.Main.run(Main.java:87)\n\tat io.cucumber.core.cli.Main.main(Main.java:30)\n","duration":511335551,"status":"failed"},"match":{"location":"stepDef.Hooks.beforeTest(io.cucumber.java.Scenario)"}}],"line":132,"name":"Test place order normal","description":"","id":"test-automation-web;test-place-order-normal","after":[{"result":{"error_message":"java.lang.NullPointerException: Cannot invoke \"org.openqa.selenium.WebDriver.quit()\" because \"helper.Utility.driver\" is null\n\tat helper.Utility.quitDriver(Utility.java:56)\n\tat stepDef.Hooks.afterTest(Hooks.java:39)\n","duration":2000468701,"status":"failed"},"match":{"location":"stepDef.Hooks.afterTest(io.cucumber.java.Scenario)"}}],"type":"scenario","keyword":"Scenario","steps":[{"result":{"duration":90288,"status":"skipped"},"line":133,"name":"user go to web page","match":{"location":"stepDef.WebStep.userGoToWebPage()"},"keyword":"Given "},{"result":{"duration":54872,"status":"skipped"},"line":134,"name":"user click sign up menu","match":{"location":"stepDef.WebStep.userClickSignUpMenu()"},"keyword":"And "},{"result":{"duration":55363,"status":"skipped"},"line":135,"name":"user input sign up username","match":{"location":"stepDef.WebStep.userInputSignUpUsername()"},"keyword":"And "},{"result":{"duration":55153,"status":"skipped"},"line":136,"name":"user input sign up pwd","match":{"location":"stepDef.WebStep.userInputSignUpPwd()"},"keyword":"And "},{"result":{"duration":52287,"status":"skipped"},"line":137,"name":"user click sign up button","match":{"location":"stepDef.WebStep.userClickSignUpButton()"},"keyword":"When "},{"result":{"duration":58048,"status":"skipped"},"line":138,"name":"validation get \"alert\" message \"Sign up successful.\"","match":{"arguments":[{"val":"\"alert\"","offset":15},{"val":"\"Sign up successful.\"","offset":31}],"location":"stepDef.WebStep.validationGetMessage(java.lang.String,java.lang.String)"},"keyword":"Then "},{"result":{"duration":52057,"status":"skipped"},"line":139,"name":"user click login menu","match":{"location":"stepDef.WebStep.userClickLoginMenu()"},"keyword":"And "},{"result":{"duration":831025,"status":"skipped"},"line":140,"name":"user input login username","match":{"location":"stepDef.WebStep.userInputLoginUsername()"},"keyword":"And "},{"result":{"duration":72705,"status":"skipped"},"line":141,"name":"user input login pwd","match":{"location":"stepDef.WebStep.userInputLoginPwd()"},"keyword":"And "},{"result":{"duration":48270,"status":"skipped"},"line":142,"name":"user click login button","match":{"location":"stepDef.WebStep.userClickLoginButton()"},"keyword":"When "},{"result":{"duration":39684,"status":"skipped"},"line":143,"name":"validation login successful","match":{"location":"stepDef.WebStep.validationLoginSuccessful()"},"keyword":"Then "},{"result":{"duration":37549,"status":"skipped"},"line":144,"name":"user click product name","match":{"location":"stepDef.WebStep.userClickProductName()"},"keyword":"And "},{"result":{"duration":43080,"status":"skipped"},"line":145,"name":"user click add to cart button","match":{"location":"stepDef.WebStep.userClickAddToCartButton()"},"keyword":"And "},{"result":{"duration":44452,"status":"skipped"},"line":146,"name":"validation get \"alert\" message \"Product added.\"","match":{"arguments":[{"val":"\"alert\"","offset":15},{"val":"\"Product added.\"","offset":31}],"location":"stepDef.WebStep.validationGetMessage(java.lang.String,java.lang.String)"},"keyword":"Then "},{"result":{"duration":43010,"status":"skipped"},"line":147,"name":"user click home menu","match":{"location":"stepDef.WebStep.userClickHomeMenu()"},"keyword":"And "},{"result":{"duration":43180,"status":"skipped"},"line":148,"name":"user click product name","match":{"location":"stepDef.WebStep.userClickProductName()"},"keyword":"And "},{"result":{"duration":41617,"status":"skipped"},"line":149,"name":"user click add to cart button","match":{"location":"stepDef.WebStep.userClickAddToCartButton()"},"keyword":"And "},{"result":{"duration":170547,"status":"skipped"},"line":150,"name":"validation get \"alert\" message \"Product added.\"","match":{"arguments":[{"val":"\"alert\"","offset":15},{"val":"\"Product added.\"","offset":31}],"location":"stepDef.WebStep.validationGetMessage(java.lang.String,java.lang.String)"},"keyword":"Then "},{"result":{"duration":56646,"status":"skipped"},"line":151,"name":"user click cart menu","match":{"location":"stepDef.WebStep.userClickCartMenu()"},"keyword":"And "},{"result":{"duration":40365,"status":"skipped"},"line":152,"name":"validation cart page display equals 2 product","match":{"arguments":[{"val":"2","offset":36}],"location":"stepDef.WebStep.validationCartPageDisplayEqualsProduct(int)"},"keyword":"Then "},{"result":{"duration":42609,"status":"skipped"},"line":153,"name":"validation total price is equals price of product","match":{"location":"stepDef.WebStep.validationTotalPriceIsEqualsPriceOfProduct()"},"keyword":"Then "},{"result":{"duration":42940,"status":"skipped"},"line":154,"name":"user click place order button","match":{"location":"stepDef.WebStep.userClickPlaceOrderButton()"},"keyword":"And "},{"result":{"duration":39443,"status":"skipped"},"line":155,"name":"user input place order information","match":{"location":"stepDef.WebStep.userInputPlaceOrderInformation()"},"keyword":"And "},{"result":{"duration":41587,"status":"skipped"},"line":156,"name":"user click purchase button","match":{"location":"stepDef.WebStep.userClickPurchaseButton()"},"keyword":"And "},{"result":{"duration":48040,"status":"skipped"},"line":157,"name":"validation get \"page\" message \"Thank you for your purchase!\"","match":{"arguments":[{"val":"\"page\"","offset":15},{"val":"\"Thank you for your purchase!\"","offset":30}],"location":"stepDef.WebStep.validationGetMessage(java.lang.String,java.lang.String)"},"keyword":"Then "},{"result":{"duration":41267,"status":"skipped"},"line":158,"name":"validation order information is match","match":{"location":"stepDef.WebStep.validationOrderInformationIsMatch()"},"keyword":"Then "},{"result":{"duration":41738,"status":"skipped"},"line":159,"name":"user click ok button","match":{"location":"stepDef.WebStep.userClickOkButton()"},"keyword":"And "},{"result":{"duration":47769,"status":"skipped"},"line":160,"name":"validation user is on home page","match":{"location":"stepDef.WebStep.validationUserIsOnHomePage()"},"keyword":"Then "}],"tags":[{"name":"@web"},{"name":"@web"}]},{"start_timestamp":"2024-02-22T17:45:40.426Z","before":[{"result":{"error_message":"io.github.bonigarcia.wdm.config.WebDriverManagerException: java.lang.NumberFormatException: For input string: \"public\"\n\tat io.github.bonigarcia.wdm.WebDriverManager.handleException(WebDriverManager.java:1445)\n\tat io.github.bonigarcia.wdm.WebDriverManager.manage(WebDriverManager.java:1205)\n\tat io.github.bonigarcia.wdm.WebDriverManager.fallback(WebDriverManager.java:1461)\n\tat io.github.bonigarcia.wdm.WebDriverManager.handleException(WebDriverManager.java:1442)\n\tat io.github.bonigarcia.wdm.WebDriverManager.manage(WebDriverManager.java:1205)\n\tat io.github.bonigarcia.wdm.WebDriverManager.handleException(WebDriverManager.java:1435)\n\tat io.github.bonigarcia.wdm.WebDriverManager.manage(WebDriverManager.java:1205)\n\tat io.github.bonigarcia.wdm.WebDriverManager.setup(WebDriverManager.java:427)\n\tat helper.Utility.startDriver(Utility.java:47)\n\tat stepDef.Hooks.beforeTest(Hooks.java:30)\nCaused by: java.lang.NumberFormatException: For input string: \"public\"\n\tat java.base/java.lang.NumberFormatException.forInputString(NumberFormatException.java:67)\n\tat java.base/java.lang.Integer.parseInt(Integer.java:662)\n\tat java.base/java.lang.Integer.parseInt(Integer.java:778)\n\tat io.github.bonigarcia.wdm.managers.ChromeDriverManager.buildUrl(ChromeDriverManager.java:178)\n\tat io.github.bonigarcia.wdm.managers.ChromeDriverManager.buildUrl(ChromeDriverManager.java:155)\n\tat io.github.bonigarcia.wdm.WebDriverManager.download(WebDriverManager.java:1282)\n\tat io.github.bonigarcia.wdm.WebDriverManager.manage(WebDriverManager.java:1199)\n\tat io.github.bonigarcia.wdm.WebDriverManager.fallback(WebDriverManager.java:1461)\n\tat io.github.bonigarcia.wdm.WebDriverManager.handleException(WebDriverManager.java:1442)\n\tat io.github.bonigarcia.wdm.WebDriverManager.manage(WebDriverManager.java:1205)\n\tat io.github.bonigarcia.wdm.WebDriverManager.handleException(WebDriverManager.java:1435)\n\tat io.github.bonigarcia.wdm.WebDriverManager.manage(WebDriverManager.java:1205)\n\tat io.github.bonigarcia.wdm.WebDriverManager.setup(WebDriverManager.java:427)\n\tat helper.Utility.startDriver(Utility.java:47)\n\tat stepDef.Hooks.beforeTest(Hooks.java:30)\n\tat java.base/jdk.internal.reflect.DirectMethodHandleAccessor.invoke(DirectMethodHandleAccessor.java:103)\n\tat java.base/java.lang.reflect.Method.invoke(Method.java:580)\n\tat io.cucumber.java.Invoker.doInvoke(Invoker.java:66)\n\tat io.cucumber.java.Invoker.invoke(Invoker.java:24)\n\tat io.cucumber.java.AbstractGlueDefinition.invokeMethod(AbstractGlueDefinition.java:47)\n\tat io.cucumber.java.JavaHookDefinition.execute(JavaHookDefinition.java:64)\n\tat io.cucumber.core.runner.CoreHookDefinition.execute(CoreHookDefinition.java:46)\n\tat io.cucumber.core.runner.HookDefinitionMatch.runStep(HookDefinitionMatch.java:21)\n\tat io.cucumber.core.runner.ExecutionMode$1.execute(ExecutionMode.java:10)\n\tat io.cucumber.core.runner.TestStep.executeStep(TestStep.java:84)\n\tat io.cucumber.core.runner.TestStep.run(TestStep.java:56)\n\tat io.cucumber.core.runner.TestCase.run(TestCase.java:78)\n\tat io.cucumber.core.runner.Runner.runPickle(Runner.java:75)\n\tat io.cucumber.core.runtime.Runtime.lambda$executePickle$6(Runtime.java:107)\n\tat io.cucumber.core.runtime.CucumberExecutionContext.lambda$runTestCase$5(CucumberExecutionContext.java:137)\n\tat io.cucumber.core.runtime.RethrowingThrowableCollector.executeAndThrow(RethrowingThrowableCollector.java:23)\n\tat io.cucumber.core.runtime.CucumberExecutionContext.runTestCase(CucumberExecutionContext.java:137)\n\tat io.cucumber.core.runtime.Runtime.lambda$executePickle$7(Runtime.java:107)\n\tat java.base/java.util.concurrent.Executors$RunnableAdapter.call(Executors.java:572)\n\tat java.base/java.util.concurrent.FutureTask.run(FutureTask.java:317)\n\tat io.cucumber.core.runtime.Runtime$SameThreadExecutorService.execute(Runtime.java:235)\n\tat java.base/java.util.concurrent.AbstractExecutorService.submit(AbstractExecutorService.java:123)\n\tat io.cucumber.core.runtime.Runtime.lambda$runFeatures$3(Runtime.java:89)\n\tat java.base/java.util.stream.ReferencePipeline$3$1.accept(ReferencePipeline.java:197)\n\tat java.base/java.util.stream.SliceOps$1$1.accept(SliceOps.java:200)\n\tat java.base/java.util.ArrayList$ArrayListSpliterator.tryAdvance(ArrayList.java:1685)\n\tat java.base/java.util.stream.ReferencePipeline.forEachWithCancel(ReferencePipeline.java:129)\n\tat java.base/java.util.stream.AbstractPipeline.copyIntoWithCancel(AbstractPipeline.java:527)\n\tat java.base/java.util.stream.AbstractPipeline.copyInto(AbstractPipeline.java:513)\n\tat java.base/java.util.stream.AbstractPipeline.wrapAndCopyInto(AbstractPipeline.java:499)\n\tat java.base/java.util.stream.ReduceOps$ReduceOp.evaluateSequential(ReduceOps.java:921)\n\tat java.base/java.util.stream.AbstractPipeline.evaluate(AbstractPipeline.java:234)\n\tat java.base/java.util.stream.ReferencePipeline.collect(ReferencePipeline.java:682)\n\tat io.cucumber.core.runtime.Runtime.runFeatures(Runtime.java:90)\n\tat io.cucumber.core.runtime.Runtime.lambda$run$0(Runtime.java:78)\n\tat io.cucumber.core.runtime.CucumberExecutionContext.lambda$runFeatures$6(CucumberExecutionContext.java:148)\n\tat io.cucumber.core.runtime.CucumberExecutionContext.execute(CucumberExecutionContext.java:163)\n\tat io.cucumber.core.runtime.CucumberExecutionContext.runFeatures(CucumberExecutionContext.java:146)\n\tat io.cucumber.core.runtime.Runtime.run(Runtime.java:78)\n\tat io.cucumber.core.cli.Main.run(Main.java:87)\n\tat io.cucumber.core.cli.Main.main(Main.java:30)\n","duration":496074177,"status":"failed"},"match":{"location":"stepDef.Hooks.beforeTest(io.cucumber.java.Scenario)"}}],"line":162,"name":"Test negative place order with no input order information","description":"","id":"test-automation-web;test-negative-place-order-with-no-input-order-information","after":[{"result":{"error_message":"java.lang.NullPointerException: Cannot invoke \"org.openqa.selenium.WebDriver.quit()\" because \"helper.Utility.driver\" is null\n\tat helper.Utility.quitDriver(Utility.java:56)\n\tat stepDef.Hooks.afterTest(Hooks.java:39)\n","duration":2000519324,"status":"failed"},"match":{"location":"stepDef.Hooks.afterTest(io.cucumber.java.Scenario)"}}],"type":"scenario","keyword":"Scenario","steps":[{"result":{"duration":72455,"status":"skipped"},"line":163,"name":"user go to web page","match":{"location":"stepDef.WebStep.userGoToWebPage()"},"keyword":"Given "},{"result":{"duration":47007,"status":"skipped"},"line":164,"name":"user click sign up menu","match":{"location":"stepDef.WebStep.userClickSignUpMenu()"},"keyword":"And "},{"result":{"duration":40455,"status":"skipped"},"line":165,"name":"user input sign up username","match":{"location":"stepDef.WebStep.userInputSignUpUsername()"},"keyword":"And "},{"result":{"duration":39393,"status":"skipped"},"line":166,"name":"user input sign up pwd","match":{"location":"stepDef.WebStep.userInputSignUpPwd()"},"keyword":"And "},{"result":{"duration":48089,"status":"skipped"},"line":167,"name":"user click sign up button","match":{"location":"stepDef.WebStep.userClickSignUpButton()"},"keyword":"When "},{"result":{"duration":36909,"status":"skipped"},"line":168,"name":"validation get \"alert\" message \"Sign up successful.\"","match":{"arguments":[{"val":"\"alert\"","offset":15},{"val":"\"Sign up successful.\"","offset":31}],"location":"stepDef.WebStep.validationGetMessage(java.lang.String,java.lang.String)"},"keyword":"Then "},{"result":{"duration":49452,"status":"skipped"},"line":169,"name":"user click login menu","match":{"location":"stepDef.WebStep.userClickLoginMenu()"},"keyword":"And "},{"result":{"duration":31929,"status":"skipped"},"line":170,"name":"user input login username","match":{"location":"stepDef.WebStep.userInputLoginUsername()"},"keyword":"And "},{"result":{"duration":28163,"status":"skipped"},"line":171,"name":"user input login pwd","match":{"location":"stepDef.WebStep.userInputLoginPwd()"},"keyword":"And "},{"result":{"duration":47608,"status":"skipped"},"line":172,"name":"user click login button","match":{"location":"stepDef.WebStep.userClickLoginButton()"},"keyword":"When "},{"result":{"duration":47378,"status":"skipped"},"line":173,"name":"validation login successful","match":{"location":"stepDef.WebStep.validationLoginSuccessful()"},"keyword":"Then "},{"result":{"duration":42589,"status":"skipped"},"line":174,"name":"user click product name","match":{"location":"stepDef.WebStep.userClickProductName()"},"keyword":"And "},{"result":{"duration":60993,"status":"skipped"},"line":175,"name":"user click add to cart button","match":{"location":"stepDef.WebStep.userClickAddToCartButton()"},"keyword":"And "},{"result":{"duration":44753,"status":"skipped"},"line":176,"name":"validation get \"alert\" message \"Product added.\"","match":{"arguments":[{"val":"\"alert\"","offset":15},{"val":"\"Product added.\"","offset":31}],"location":"stepDef.WebStep.validationGetMessage(java.lang.String,java.lang.String)"},"keyword":"Then "},{"result":{"duration":63217,"status":"skipped"},"line":177,"name":"user click home menu","match":{"location":"stepDef.WebStep.userClickHomeMenu()"},"keyword":"And "},{"result":{"duration":85869,"status":"skipped"},"line":178,"name":"user click product name","match":{"location":"stepDef.WebStep.userClickProductName()"},"keyword":"And "},{"result":{"duration":49021,"status":"skipped"},"line":179,"name":"user click add to cart button","match":{"location":"stepDef.WebStep.userClickAddToCartButton()"},"keyword":"And "},{"result":{"duration":46727,"status":"skipped"},"line":180,"name":"validation get \"alert\" message \"Product added.\"","match":{"arguments":[{"val":"\"alert\"","offset":15},{"val":"\"Product added.\"","offset":31}],"location":"stepDef.WebStep.validationGetMessage(java.lang.String,java.lang.String)"},"keyword":"Then "},{"result":{"duration":49082,"status":"skipped"},"line":181,"name":"user click cart menu","match":{"location":"stepDef.WebStep.userClickCartMenu()"},"keyword":"And "},{"result":{"duration":63388,"status":"skipped"},"line":182,"name":"validation cart page display equals 2 product","match":{"arguments":[{"val":"2","offset":36}],"location":"stepDef.WebStep.validationCartPageDisplayEqualsProduct(int)"},"keyword":"Then "},{"result":{"duration":48290,"status":"skipped"},"line":183,"name":"validation total price is equals price of product","match":{"location":"stepDef.WebStep.validationTotalPriceIsEqualsPriceOfProduct()"},"keyword":"Then "},{"result":{"duration":46707,"status":"skipped"},"line":184,"name":"user click place order button","match":{"location":"stepDef.WebStep.userClickPlaceOrderButton()"},"keyword":"And "},{"result":{"duration":35285,"status":"skipped"},"line":185,"name":"user click purchase button","match":{"location":"stepDef.WebStep.userClickPurchaseButton()"},"keyword":"And "},{"result":{"duration":43230,"status":"skipped"},"line":186,"name":"validation get \"alert\" message \"Please fill out Name and Creditcard.\"","match":{"arguments":[{"val":"\"alert\"","offset":15},{"val":"\"Please fill out Name and Creditcard.\"","offset":31}],"location":"stepDef.WebStep.validationGetMessage(java.lang.String,java.lang.String)"},"keyword":"Then "}],"tags":[{"name":"@web"}]}],"name":"Test Automation Web","description":"","id":"test-automation-web","keyword":"Feature","uri":"file:src/test/java/features/web.feature","tags":[{"name":"@web","type":"Tag","location":{"line":1,"column":1}}]}]