[{"line":2,"elements":[{"start_timestamp":"2024-02-23T15:50:24.547Z","before":[{"result":{"duration":2245751459,"status":"passed"},"match":{"location":"stepDef.Hooks.beforeTest(io.cucumber.java.Scenario)"}}],"line":5,"name":"Test sign up normal","description":"","id":"test-automation-web;test-sign-up-normal","after":[{"result":{"duration":2072686539,"status":"passed"},"match":{"location":"stepDef.Hooks.afterTest(io.cucumber.java.Scenario)"}}],"type":"scenario","keyword":"Scenario","steps":[{"result":{"duration":697517015,"status":"passed"},"line":6,"name":"user go to web page","match":{"location":"stepDef.WebStep.userGoToWebPage()"},"keyword":"Given "},{"result":{"duration":62167065,"status":"passed"},"line":7,"name":"user click sign up menu","match":{"location":"stepDef.WebStep.userClickSignUpMenu()"},"keyword":"And "},{"result":{"duration":284635021,"status":"passed"},"line":8,"name":"user input sign up username","match":{"location":"stepDef.WebStep.userInputSignUpUsername()"},"keyword":"And "},{"result":{"duration":88396242,"status":"passed"},"line":9,"name":"user input sign up pwd","match":{"location":"stepDef.WebStep.userInputSignUpPwd()"},"keyword":"And "},{"result":{"duration":61603778,"status":"passed"},"line":10,"name":"user click sign up button","match":{"location":"stepDef.WebStep.userClickSignUpButton()"},"keyword":"When "},{"result":{"duration":557034487,"status":"passed"},"line":11,"name":"validation get \"alert\" message \"Sign up successful.\"","match":{"arguments":[{"val":"\"alert\"","offset":15},{"val":"\"Sign up successful.\"","offset":31}],"location":"stepDef.WebStep.validationGetMessage(java.lang.String,java.lang.String)"},"keyword":"Then "}],"tags":[{"name":"@web"},{"name":"@web"}]},{"start_timestamp":"2024-02-23T15:50:30.647Z","before":[{"result":{"duration":321639280,"status":"passed"},"match":{"location":"stepDef.Hooks.beforeTest(io.cucumber.java.Scenario)"}}],"line":14,"name":"Test negative sign up user not input sign up username and password","description":"","id":"test-automation-web;test-negative-sign-up-user-not-input-sign-up-username-and-password","after":[{"result":{"duration":2201191472,"status":"passed"},"match":{"location":"stepDef.Hooks.afterTest(io.cucumber.java.Scenario)"}}],"type":"scenario","keyword":"Scenario","steps":[{"result":{"duration":319728912,"status":"passed"},"line":15,"name":"user go to web page","match":{"location":"stepDef.WebStep.userGoToWebPage()"},"keyword":"Given "},{"result":{"duration":68135405,"status":"passed"},"line":16,"name":"user click sign up menu","match":{"location":"stepDef.WebStep.userClickSignUpMenu()"},"keyword":"And "},{"result":{"duration":169454207,"status":"passed"},"line":17,"name":"user click sign up button","match":{"location":"stepDef.WebStep.userClickSignUpButton()"},"keyword":"When "},{"result":{"duration":15083129,"status":"passed"},"line":18,"name":"validation get \"alert\" message \"Please fill out Username and Password.\"","match":{"arguments":[{"val":"\"alert\"","offset":15},{"val":"\"Please fill out Username and Password.\"","offset":31}],"location":"stepDef.WebStep.validationGetMessage(java.lang.String,java.lang.String)"},"keyword":"Then "}],"tags":[{"name":"@web"},{"name":"@web"}]},{"start_timestamp":"2024-02-23T15:50:33.752Z","before":[{"result":{"duration":269055955,"status":"passed"},"match":{"location":"stepDef.Hooks.beforeTest(io.cucumber.java.Scenario)"}}],"line":21,"name":"Test login normal","description":"","id":"test-automation-web;test-login-normal","after":[{"result":{"duration":2069113946,"status":"passed"},"match":{"location":"stepDef.Hooks.afterTest(io.cucumber.java.Scenario)"}}],"type":"scenario","keyword":"Scenario","steps":[{"result":{"duration":247135140,"status":"passed"},"line":22,"name":"user go to web page","match":{"location":"stepDef.WebStep.userGoToWebPage()"},"keyword":"Given "},{"result":{"duration":78587011,"status":"passed"},"line":23,"name":"user click sign up menu","match":{"location":"stepDef.WebStep.userClickSignUpMenu()"},"keyword":"And "},{"result":{"duration":271758616,"status":"passed"},"line":24,"name":"user input sign up username","match":{"location":"stepDef.WebStep.userInputSignUpUsername()"},"keyword":"And "},{"result":{"duration":44660165,"status":"passed"},"line":25,"name":"user input sign up pwd","match":{"location":"stepDef.WebStep.userInputSignUpPwd()"},"keyword":"And "},{"result":{"duration":37737957,"status":"passed"},"line":26,"name":"user click sign up button","match":{"location":"stepDef.WebStep.userClickSignUpButton()"},"keyword":"When "},{"result":{"duration":517938322,"status":"passed"},"line":27,"name":"validation get \"alert\" message \"Sign up successful.\"","match":{"arguments":[{"val":"\"alert\"","offset":15},{"val":"\"Sign up successful.\"","offset":31}],"location":"stepDef.WebStep.validationGetMessage(java.lang.String,java.lang.String)"},"keyword":"Then "},{"result":{"duration":158986013,"status":"passed"},"line":28,"name":"user click login menu","match":{"location":"stepDef.WebStep.userClickLoginMenu()"},"keyword":"And "},{"result":{"duration":254360910,"status":"passed"},"line":29,"name":"user input login username","match":{"location":"stepDef.WebStep.userInputLoginUsername()"},"keyword":"And "},{"result":{"duration":42734838,"status":"passed"},"line":30,"name":"user input login pwd","match":{"location":"stepDef.WebStep.userInputLoginPwd()"},"keyword":"And "},{"result":{"duration":36782506,"status":"passed"},"line":31,"name":"user click login button","match":{"location":"stepDef.WebStep.userClickLoginButton()"},"keyword":"When "},{"result":{"duration":2019916886,"status":"passed"},"line":32,"name":"validation login successful","match":{"location":"stepDef.WebStep.validationLoginSuccessful()"},"keyword":"Then "}],"tags":[{"name":"@web"},{"name":"@web"}]},{"start_timestamp":"2024-02-23T15:50:39.808Z","before":[{"result":{"duration":253899233,"status":"passed"},"match":{"location":"stepDef.Hooks.beforeTest(io.cucumber.java.Scenario)"}}],"line":35,"name":"Test negative login user not input login username and password","description":"","id":"test-automation-web;test-negative-login-user-not-input-login-username-and-password","after":[{"result":{"duration":2068762059,"status":"passed"},"match":{"location":"stepDef.Hooks.afterTest(io.cucumber.java.Scenario)"}}],"type":"scenario","keyword":"Scenario","steps":[{"result":{"duration":258840417,"status":"passed"},"line":36,"name":"user go to web page","match":{"location":"stepDef.WebStep.userGoToWebPage()"},"keyword":"Given "},{"result":{"duration":99024565,"status":"passed"},"line":37,"name":"user click login menu","match":{"location":"stepDef.WebStep.userClickLoginMenu()"},"keyword":"And "},{"result":{"duration":212410189,"status":"passed"},"line":38,"name":"user click login button","match":{"location":"stepDef.WebStep.userClickLoginButton()"},"keyword":"When "},{"result":{"duration":12631174,"status":"passed"},"line":39,"name":"validation get \"alert\" message \"Please fill out Username and Password.\"","match":{"arguments":[{"val":"\"alert\"","offset":15},{"val":"\"Please fill out Username and Password.\"","offset":31}],"location":"stepDef.WebStep.validationGetMessage(java.lang.String,java.lang.String)"},"keyword":"Then "}],"tags":[{"name":"@web"},{"name":"@web"}]},{"start_timestamp":"2024-02-23T15:50:42.721Z","before":[{"result":{"duration":260135568,"status":"passed"},"match":{"location":"stepDef.Hooks.beforeTest(io.cucumber.java.Scenario)"}}],"line":42,"name":"Test logout normal","description":"","id":"test-automation-web;test-logout-normal","after":[{"result":{"duration":2068830695,"status":"passed"},"match":{"location":"stepDef.Hooks.afterTest(io.cucumber.java.Scenario)"}}],"type":"scenario","keyword":"Scenario","steps":[{"result":{"duration":269518762,"status":"passed"},"line":43,"name":"user go to web page","match":{"location":"stepDef.WebStep.userGoToWebPage()"},"keyword":"Given "},{"result":{"duration":70064566,"status":"passed"},"line":44,"name":"user click sign up menu","match":{"location":"stepDef.WebStep.userClickSignUpMenu()"},"keyword":"And "},{"result":{"duration":179318908,"status":"passed"},"line":45,"name":"user input sign up username","match":{"location":"stepDef.WebStep.userInputSignUpUsername()"},"keyword":"And "},{"result":{"duration":43990757,"status":"passed"},"line":46,"name":"user input sign up pwd","match":{"location":"stepDef.WebStep.userInputSignUpPwd()"},"keyword":"And "},{"result":{"duration":37974198,"status":"passed"},"line":47,"name":"user click sign up button","match":{"location":"stepDef.WebStep.userClickSignUpButton()"},"keyword":"When "},{"result":{"duration":518412679,"status":"passed"},"line":48,"name":"validation get \"alert\" message \"Sign up successful.\"","match":{"arguments":[{"val":"\"alert\"","offset":15},{"val":"\"Sign up successful.\"","offset":31}],"location":"stepDef.WebStep.validationGetMessage(java.lang.String,java.lang.String)"},"keyword":"Then "},{"result":{"duration":36169963,"status":"passed"},"line":49,"name":"user click login menu","match":{"location":"stepDef.WebStep.userClickLoginMenu()"},"keyword":"And "},{"result":{"duration":257635970,"status":"passed"},"line":50,"name":"user input login username","match":{"location":"stepDef.WebStep.userInputLoginUsername()"},"keyword":"And "},{"result":{"duration":44753138,"status":"passed"},"line":51,"name":"user input login pwd","match":{"location":"stepDef.WebStep.userInputLoginPwd()"},"keyword":"And "},{"result":{"duration":34563191,"status":"passed"},"line":52,"name":"user click login button","match":{"location":"stepDef.WebStep.userClickLoginButton()"},"keyword":"When "},{"result":{"duration":2020204432,"status":"passed"},"line":53,"name":"validation login successful","match":{"location":"stepDef.WebStep.validationLoginSuccessful()"},"keyword":"Then "},{"result":{"duration":1144216451,"status":"passed"},"line":54,"name":"user click logout button","match":{"location":"stepDef.WebStep.userClickLogoutButton()"},"keyword":"And "},{"result":{"duration":55095924,"status":"passed"},"line":55,"name":"validation logout successful","match":{"location":"stepDef.WebStep.validationLogoutSuccessful()"},"keyword":"Then "}],"tags":[{"name":"@web"},{"name":"@web"}]},{"start_timestamp":"2024-02-23T15:50:49.773Z","before":[{"result":{"duration":251194093,"status":"passed"},"match":{"location":"stepDef.Hooks.beforeTest(io.cucumber.java.Scenario)"}}],"line":58,"name":"Test sort by product categories normal","description":"","id":"test-automation-web;test-sort-by-product-categories-normal","after":[{"result":{"duration":2068740562,"status":"passed"},"match":{"location":"stepDef.Hooks.afterTest(io.cucumber.java.Scenario)"}}],"type":"scenario","keyword":"Scenario","steps":[{"result":{"duration":314876674,"status":"passed"},"line":59,"name":"user go to web page","match":{"location":"stepDef.WebStep.userGoToWebPage()"},"keyword":"Given "},{"result":{"duration":72695882,"status":"passed"},"line":60,"name":"user click sign up menu","match":{"location":"stepDef.WebStep.userClickSignUpMenu()"},"keyword":"And "},{"result":{"duration":175871793,"status":"passed"},"line":61,"name":"user input sign up username","match":{"location":"stepDef.WebStep.userInputSignUpUsername()"},"keyword":"And "},{"result":{"duration":44215695,"status":"passed"},"line":62,"name":"user input sign up pwd","match":{"location":"stepDef.WebStep.userInputSignUpPwd()"},"keyword":"And "},{"result":{"duration":36912821,"status":"passed"},"line":63,"name":"user click sign up button","match":{"location":"stepDef.WebStep.userClickSignUpButton()"},"keyword":"When "},{"result":{"duration":518648548,"status":"passed"},"line":64,"name":"validation get \"alert\" message \"Sign up successful.\"","match":{"arguments":[{"val":"\"alert\"","offset":15},{"val":"\"Sign up successful.\"","offset":31}],"location":"stepDef.WebStep.validationGetMessage(java.lang.String,java.lang.String)"},"keyword":"Then "},{"result":{"duration":48802911,"status":"passed"},"line":65,"name":"user click login menu","match":{"location":"stepDef.WebStep.userClickLoginMenu()"},"keyword":"And "},{"result":{"duration":254743564,"status":"passed"},"line":66,"name":"user input login username","match":{"location":"stepDef.WebStep.userInputLoginUsername()"},"keyword":"And "},{"result":{"duration":42700895,"status":"passed"},"line":67,"name":"user input login pwd","match":{"location":"stepDef.WebStep.userInputLoginPwd()"},"keyword":"And "},{"result":{"duration":39329091,"status":"passed"},"line":68,"name":"user click login button","match":{"location":"stepDef.WebStep.userClickLoginButton()"},"keyword":"When "},{"result":{"duration":2019296756,"status":"passed"},"line":69,"name":"validation login successful","match":{"location":"stepDef.WebStep.validationLoginSuccessful()"},"keyword":"Then "},{"result":{"duration":1034569459,"status":"passed"},"line":70,"name":"user click categories \"Phones\"","match":{"arguments":[{"val":"\"Phones\"","offset":22}],"location":"stepDef.WebStep.userClickCategories(java.lang.String)"},"keyword":"And "},{"result":{"duration":1018400408,"status":"passed"},"line":71,"name":"validation page display \"Phones\" product","match":{"arguments":[{"val":"\"Phones\"","offset":24}],"location":"stepDef.WebStep.validationPageDisplayProduct(java.lang.String)"},"keyword":"Then "},{"result":{"duration":1031803266,"status":"passed"},"line":72,"name":"user click categories \"Laptops\"","match":{"arguments":[{"val":"\"Laptops\"","offset":22}],"location":"stepDef.WebStep.userClickCategories(java.lang.String)"},"keyword":"And "},{"result":{"duration":1013989549,"status":"passed"},"line":73,"name":"validation page display \"Laptops\" product","match":{"arguments":[{"val":"\"Laptops\"","offset":24}],"location":"stepDef.WebStep.validationPageDisplayProduct(java.lang.String)"},"keyword":"Then "},{"result":{"duration":1033488612,"status":"passed"},"line":74,"name":"user click categories \"Monitors\"","match":{"arguments":[{"val":"\"Monitors\"","offset":22}],"location":"stepDef.WebStep.userClickCategories(java.lang.String)"},"keyword":"And "},{"result":{"duration":1014014453,"status":"passed"},"line":75,"name":"validation page display \"Monitors\" product","match":{"arguments":[{"val":"\"Monitors\"","offset":24}],"location":"stepDef.WebStep.validationPageDisplayProduct(java.lang.String)"},"keyword":"Then "}],"tags":[{"name":"@web"},{"name":"@web"}]},{"start_timestamp":"2024-02-23T15:51:01.819Z","before":[{"result":{"duration":263584895,"status":"passed"},"match":{"location":"stepDef.Hooks.beforeTest(io.cucumber.java.Scenario)"}}],"line":78,"name":"Test add to cart normal","description":"","id":"test-automation-web;test-add-to-cart-normal","after":[{"result":{"duration":2069333829,"status":"passed"},"match":{"location":"stepDef.Hooks.afterTest(io.cucumber.java.Scenario)"}}],"type":"scenario","keyword":"Scenario","steps":[{"result":{"duration":298972790,"status":"passed"},"line":79,"name":"user go to web page","match":{"location":"stepDef.WebStep.userGoToWebPage()"},"keyword":"Given "},{"result":{"duration":79926496,"status":"passed"},"line":80,"name":"user click sign up menu","match":{"location":"stepDef.WebStep.userClickSignUpMenu()"},"keyword":"And "},{"result":{"duration":194936341,"status":"passed"},"line":81,"name":"user input sign up username","match":{"location":"stepDef.WebStep.userInputSignUpUsername()"},"keyword":"And "},{"result":{"duration":47884533,"status":"passed"},"line":82,"name":"user input sign up pwd","match":{"location":"stepDef.WebStep.userInputSignUpPwd()"},"keyword":"And "},{"result":{"duration":37143125,"status":"passed"},"line":83,"name":"user click sign up button","match":{"location":"stepDef.WebStep.userClickSignUpButton()"},"keyword":"When "},{"result":{"duration":517337649,"status":"passed"},"line":84,"name":"validation get \"alert\" message \"Sign up successful.\"","match":{"arguments":[{"val":"\"alert\"","offset":15},{"val":"\"Sign up successful.\"","offset":31}],"location":"stepDef.WebStep.validationGetMessage(java.lang.String,java.lang.String)"},"keyword":"Then "},{"result":{"duration":102797104,"status":"passed"},"line":85,"name":"user click login menu","match":{"location":"stepDef.WebStep.userClickLoginMenu()"},"keyword":"And "},{"result":{"duration":256848221,"status":"passed"},"line":86,"name":"user input login username","match":{"location":"stepDef.WebStep.userInputLoginUsername()"},"keyword":"And "},{"result":{"duration":44573389,"status":"passed"},"line":87,"name":"user input login pwd","match":{"location":"stepDef.WebStep.userInputLoginPwd()"},"keyword":"And "},{"result":{"duration":34691558,"status":"passed"},"line":88,"name":"user click login button","match":{"location":"stepDef.WebStep.userClickLoginButton()"},"keyword":"When "},{"result":{"duration":2019845449,"status":"passed"},"line":89,"name":"validation login successful","match":{"location":"stepDef.WebStep.validationLoginSuccessful()"},"keyword":"Then "},{"result":{"duration":176169538,"status":"passed"},"line":90,"name":"user click product name","match":{"location":"stepDef.WebStep.userClickProductName()"},"keyword":"And "},{"result":{"duration":219295231,"status":"passed"},"line":91,"name":"user click add to cart button","match":{"location":"stepDef.WebStep.userClickAddToCartButton()"},"keyword":"And "},{"result":{"duration":516580607,"status":"passed"},"line":92,"name":"validation get \"alert\" message \"Product added.\"","match":{"arguments":[{"val":"\"alert\"","offset":15},{"val":"\"Product added.\"","offset":31}],"location":"stepDef.WebStep.validationGetMessage(java.lang.String,java.lang.String)"},"keyword":"Then "},{"result":{"duration":138666541,"status":"passed"},"line":93,"name":"user click home menu","match":{"location":"stepDef.WebStep.userClickHomeMenu()"},"keyword":"And "},{"result":{"duration":273149149,"status":"passed"},"line":94,"name":"user click product name","match":{"location":"stepDef.WebStep.userClickProductName()"},"keyword":"And "},{"result":{"duration":155992817,"status":"passed"},"line":95,"name":"user click add to cart button","match":{"location":"stepDef.WebStep.userClickAddToCartButton()"},"keyword":"And "},{"result":{"duration":516813347,"status":"passed"},"line":96,"name":"validation get \"alert\" message \"Product added.\"","match":{"arguments":[{"val":"\"alert\"","offset":15},{"val":"\"Product added.\"","offset":31}],"location":"stepDef.WebStep.validationGetMessage(java.lang.String,java.lang.String)"},"keyword":"Then "},{"result":{"duration":184859505,"status":"passed"},"line":97,"name":"user click cart menu","match":{"location":"stepDef.WebStep.userClickCartMenu()"},"keyword":"And "},{"result":{"duration":2014833074,"status":"passed"},"line":98,"name":"validation cart page display equals 2 product","match":{"arguments":[{"val":"2","offset":36}],"location":"stepDef.WebStep.validationCartPageDisplayEqualsProduct(int)"},"keyword":"Then "},{"result":{"duration":35349865,"status":"passed"},"line":99,"name":"validation total price is equals price of product","match":{"location":"stepDef.WebStep.validationTotalPriceIsEqualsPriceOfProduct()"},"keyword":"Then "}],"tags":[{"name":"@web"},{"name":"@web"}]},{"start_timestamp":"2024-02-23T15:51:12.030Z","before":[{"result":{"duration":250058964,"status":"passed"},"match":{"location":"stepDef.Hooks.beforeTest(io.cucumber.java.Scenario)"}}],"line":102,"name":"Test delete product from cart","description":"","id":"test-automation-web;test-delete-product-from-cart","after":[{"result":{"duration":2069151873,"status":"passed"},"match":{"location":"stepDef.Hooks.afterTest(io.cucumber.java.Scenario)"}}],"type":"scenario","keyword":"Scenario","steps":[{"result":{"duration":301187184,"status":"passed"},"line":103,"name":"user go to web page","match":{"location":"stepDef.WebStep.userGoToWebPage()"},"keyword":"Given "},{"result":{"duration":80967968,"status":"passed"},"line":104,"name":"user click sign up menu","match":{"location":"stepDef.WebStep.userClickSignUpMenu()"},"keyword":"And "},{"result":{"duration":176648750,"status":"passed"},"line":105,"name":"user input sign up username","match":{"location":"stepDef.WebStep.userInputSignUpUsername()"},"keyword":"And "},{"result":{"duration":52708703,"status":"passed"},"line":106,"name":"user input sign up pwd","match":{"location":"stepDef.WebStep.userInputSignUpPwd()"},"keyword":"And "},{"result":{"duration":35100721,"status":"passed"},"line":107,"name":"user click sign up button","match":{"location":"stepDef.WebStep.userClickSignUpButton()"},"keyword":"When "},{"result":{"duration":518142070,"status":"passed"},"line":108,"name":"validation get \"alert\" message \"Sign up successful.\"","match":{"arguments":[{"val":"\"alert\"","offset":15},{"val":"\"Sign up successful.\"","offset":31}],"location":"stepDef.WebStep.validationGetMessage(java.lang.String,java.lang.String)"},"keyword":"Then "},{"result":{"duration":39692671,"status":"passed"},"line":109,"name":"user click login menu","match":{"location":"stepDef.WebStep.userClickLoginMenu()"},"keyword":"And "},{"result":{"duration":254071105,"status":"passed"},"line":110,"name":"user input login username","match":{"location":"stepDef.WebStep.userInputLoginUsername()"},"keyword":"And "},{"result":{"duration":43612347,"status":"passed"},"line":111,"name":"user input login pwd","match":{"location":"stepDef.WebStep.userInputLoginPwd()"},"keyword":"And "},{"result":{"duration":36478455,"status":"passed"},"line":112,"name":"user click login button","match":{"location":"stepDef.WebStep.userClickLoginButton()"},"keyword":"When "},{"result":{"duration":2019279939,"status":"passed"},"line":113,"name":"validation login successful","match":{"location":"stepDef.WebStep.validationLoginSuccessful()"},"keyword":"Then "},{"result":{"duration":175332081,"status":"passed"},"line":114,"name":"user click product name","match":{"location":"stepDef.WebStep.userClickProductName()"},"keyword":"And "},{"result":{"duration":274784822,"status":"passed"},"line":115,"name":"user click add to cart button","match":{"location":"stepDef.WebStep.userClickAddToCartButton()"},"keyword":"And "},{"result":{"duration":517164055,"status":"passed"},"line":116,"name":"validation get \"alert\" message \"Product added.\"","match":{"arguments":[{"val":"\"alert\"","offset":15},{"val":"\"Product added.\"","offset":31}],"location":"stepDef.WebStep.validationGetMessage(java.lang.String,java.lang.String)"},"keyword":"Then "},{"result":{"duration":132617472,"status":"passed"},"line":117,"name":"user click home menu","match":{"location":"stepDef.WebStep.userClickHomeMenu()"},"keyword":"And "},{"result":{"duration":264399323,"status":"passed"},"line":118,"name":"user click product name","match":{"location":"stepDef.WebStep.userClickProductName()"},"keyword":"And "},{"result":{"duration":157794812,"status":"passed"},"line":119,"name":"user click add to cart button","match":{"location":"stepDef.WebStep.userClickAddToCartButton()"},"keyword":"And "},{"result":{"duration":516953741,"status":"passed"},"line":120,"name":"validation get \"alert\" message \"Product added.\"","match":{"arguments":[{"val":"\"alert\"","offset":15},{"val":"\"Product added.\"","offset":31}],"location":"stepDef.WebStep.validationGetMessage(java.lang.String,java.lang.String)"},"keyword":"Then "},{"result":{"duration":217264810,"status":"passed"},"line":121,"name":"user click cart menu","match":{"location":"stepDef.WebStep.userClickCartMenu()"},"keyword":"And "},{"result":{"duration":2010543523,"status":"passed"},"line":122,"name":"validation cart page display equals 2 product","match":{"arguments":[{"val":"2","offset":36}],"location":"stepDef.WebStep.validationCartPageDisplayEqualsProduct(int)"},"keyword":"Then "},{"result":{"duration":34887983,"status":"passed"},"line":123,"name":"validation total price is equals price of product","match":{"location":"stepDef.WebStep.validationTotalPriceIsEqualsPriceOfProduct()"},"keyword":"Then "},{"result":{"duration":1034080319,"status":"passed"},"line":124,"name":"user click delete product from cart","match":{"location":"stepDef.WebStep.userClickDeleteProductFromCart()"},"keyword":"And "},{"result":{"duration":2007471348,"status":"passed"},"line":125,"name":"validation cart page display equals 1 product","match":{"arguments":[{"val":"1","offset":36}],"location":"stepDef.WebStep.validationCartPageDisplayEqualsProduct(int)"},"keyword":"Then "},{"result":{"duration":23730086,"status":"passed"},"line":126,"name":"validation total price is equals price of product","match":{"location":"stepDef.WebStep.validationTotalPriceIsEqualsPriceOfProduct()"},"keyword":"Then "},{"result":{"duration":1027793070,"status":"passed"},"line":127,"name":"user click delete product from cart","match":{"location":"stepDef.WebStep.userClickDeleteProductFromCart()"},"keyword":"And "},{"result":{"duration":5007235489,"status":"passed"},"line":128,"name":"validation cart page display equals 0 product","match":{"arguments":[{"val":"0","offset":36}],"location":"stepDef.WebStep.validationCartPageDisplayEqualsProduct(int)"},"keyword":"Then "},{"result":{"duration":3021717629,"status":"passed"},"line":129,"name":"validation total price is equals price of product","match":{"location":"stepDef.WebStep.validationTotalPriceIsEqualsPriceOfProduct()"},"keyword":"Then "}],"tags":[{"name":"@web"},{"name":"@web"}]},{"start_timestamp":"2024-02-23T15:51:34.345Z","before":[{"result":{"duration":249119177,"status":"passed"},"match":{"location":"stepDef.Hooks.beforeTest(io.cucumber.java.Scenario)"}}],"line":132,"name":"Test place order normal","description":"","id":"test-automation-web;test-place-order-normal","after":[{"result":{"duration":2069475997,"status":"passed"},"match":{"location":"stepDef.Hooks.afterTest(io.cucumber.java.Scenario)"}}],"type":"scenario","keyword":"Scenario","steps":[{"result":{"duration":302697643,"status":"passed"},"line":133,"name":"user go to web page","match":{"location":"stepDef.WebStep.userGoToWebPage()"},"keyword":"Given "},{"result":{"duration":88739852,"status":"passed"},"line":134,"name":"user click sign up menu","match":{"location":"stepDef.WebStep.userClickSignUpMenu()"},"keyword":"And "},{"result":{"duration":182097459,"status":"passed"},"line":135,"name":"user input sign up username","match":{"location":"stepDef.WebStep.userInputSignUpUsername()"},"keyword":"And "},{"result":{"duration":50859389,"status":"passed"},"line":136,"name":"user input sign up pwd","match":{"location":"stepDef.WebStep.userInputSignUpPwd()"},"keyword":"And "},{"result":{"duration":40733976,"status":"passed"},"line":137,"name":"user click sign up button","match":{"location":"stepDef.WebStep.userClickSignUpButton()"},"keyword":"When "},{"result":{"duration":518031897,"status":"passed"},"line":138,"name":"validation get \"alert\" message \"Sign up successful.\"","match":{"arguments":[{"val":"\"alert\"","offset":15},{"val":"\"Sign up successful.\"","offset":31}],"location":"stepDef.WebStep.validationGetMessage(java.lang.String,java.lang.String)"},"keyword":"Then "},{"result":{"duration":35475566,"status":"passed"},"line":139,"name":"user click login menu","match":{"location":"stepDef.WebStep.userClickLoginMenu()"},"keyword":"And "},{"result":{"duration":255511633,"status":"passed"},"line":140,"name":"user input login username","match":{"location":"stepDef.WebStep.userInputLoginUsername()"},"keyword":"And "},{"result":{"duration":45635354,"status":"passed"},"line":141,"name":"user input login pwd","match":{"location":"stepDef.WebStep.userInputLoginPwd()"},"keyword":"And "},{"result":{"duration":34053258,"status":"passed"},"line":142,"name":"user click login button","match":{"location":"stepDef.WebStep.userClickLoginButton()"},"keyword":"When "},{"result":{"duration":2019143417,"status":"passed"},"line":143,"name":"validation login successful","match":{"location":"stepDef.WebStep.validationLoginSuccessful()"},"keyword":"Then "},{"result":{"duration":176034471,"status":"passed"},"line":144,"name":"user click product name","match":{"location":"stepDef.WebStep.userClickProductName()"},"keyword":"And "},{"result":{"duration":219680594,"status":"passed"},"line":145,"name":"user click add to cart button","match":{"location":"stepDef.WebStep.userClickAddToCartButton()"},"keyword":"And "},{"result":{"duration":516018860,"status":"passed"},"line":146,"name":"validation get \"alert\" message \"Product added.\"","match":{"arguments":[{"val":"\"alert\"","offset":15},{"val":"\"Product added.\"","offset":31}],"location":"stepDef.WebStep.validationGetMessage(java.lang.String,java.lang.String)"},"keyword":"Then "},{"result":{"duration":119476619,"status":"passed"},"line":147,"name":"user click home menu","match":{"location":"stepDef.WebStep.userClickHomeMenu()"},"keyword":"And "},{"result":{"duration":277159286,"status":"passed"},"line":148,"name":"user click product name","match":{"location":"stepDef.WebStep.userClickProductName()"},"keyword":"And "},{"result":{"duration":162079191,"status":"passed"},"line":149,"name":"user click add to cart button","match":{"location":"stepDef.WebStep.userClickAddToCartButton()"},"keyword":"And "},{"result":{"duration":515864649,"status":"passed"},"line":150,"name":"validation get \"alert\" message \"Product added.\"","match":{"arguments":[{"val":"\"alert\"","offset":15},{"val":"\"Product added.\"","offset":31}],"location":"stepDef.WebStep.validationGetMessage(java.lang.String,java.lang.String)"},"keyword":"Then "},{"result":{"duration":184521498,"status":"passed"},"line":151,"name":"user click cart menu","match":{"location":"stepDef.WebStep.userClickCartMenu()"},"keyword":"And "},{"result":{"duration":2010612787,"status":"passed"},"line":152,"name":"validation cart page display equals 2 product","match":{"arguments":[{"val":"2","offset":36}],"location":"stepDef.WebStep.validationCartPageDisplayEqualsProduct(int)"},"keyword":"Then "},{"result":{"duration":32832453,"status":"passed"},"line":153,"name":"validation total price is equals price of product","match":{"location":"stepDef.WebStep.validationTotalPriceIsEqualsPriceOfProduct()"},"keyword":"Then "},{"result":{"duration":31991220,"status":"passed"},"line":154,"name":"user click place order button","match":{"location":"stepDef.WebStep.userClickPlaceOrderButton()"},"keyword":"And "},{"result":{"duration":474733023,"status":"passed"},"line":155,"name":"user input place order information","match":{"location":"stepDef.WebStep.userInputPlaceOrderInformation()"},"keyword":"And "},{"result":{"duration":38707310,"status":"passed"},"line":156,"name":"user click purchase button","match":{"location":"stepDef.WebStep.userClickPurchaseButton()"},"keyword":"And "},{"result":{"duration":9731143,"status":"passed"},"line":157,"name":"validation get \"page\" message \"Thank you for your purchase!\"","match":{"arguments":[{"val":"\"page\"","offset":15},{"val":"\"Thank you for your purchase!\"","offset":30}],"location":"stepDef.WebStep.validationGetMessage(java.lang.String,java.lang.String)"},"keyword":"Then "},{"result":{"duration":23705506,"status":"passed"},"line":158,"name":"validation order information is match","match":{"location":"stepDef.WebStep.validationOrderInformationIsMatch()"},"keyword":"Then "},{"result":{"duration":37338150,"status":"passed"},"line":159,"name":"user click ok button","match":{"location":"stepDef.WebStep.userClickOkButton()"},"keyword":"And "},{"result":{"duration":22557570,"status":"passed"},"line":160,"name":"validation user is on home page","match":{"location":"stepDef.WebStep.validationUserIsOnHomePage()"},"keyword":"Then "}],"tags":[{"name":"@web"},{"name":"@web"}]},{"start_timestamp":"2024-02-23T15:51:45.103Z","before":[{"result":{"duration":249994489,"status":"passed"},"match":{"location":"stepDef.Hooks.beforeTest(io.cucumber.java.Scenario)"}}],"line":162,"name":"Test negative place order with no input order information","description":"","id":"test-automation-web;test-negative-place-order-with-no-input-order-information","after":[{"result":{"duration":2068873700,"status":"passed"},"match":{"location":"stepDef.Hooks.afterTest(io.cucumber.java.Scenario)"}}],"type":"scenario","keyword":"Scenario","steps":[{"result":{"duration":288804031,"status":"passed"},"line":163,"name":"user go to web page","match":{"location":"stepDef.WebStep.userGoToWebPage()"},"keyword":"Given "},{"result":{"duration":73910270,"status":"passed"},"line":164,"name":"user click sign up menu","match":{"location":"stepDef.WebStep.userClickSignUpMenu()"},"keyword":"And "},{"result":{"duration":189957824,"status":"passed"},"line":165,"name":"user input sign up username","match":{"location":"stepDef.WebStep.userInputSignUpUsername()"},"keyword":"And "},{"result":{"duration":45275597,"status":"passed"},"line":166,"name":"user input sign up pwd","match":{"location":"stepDef.WebStep.userInputSignUpPwd()"},"keyword":"And "},{"result":{"duration":36553841,"status":"passed"},"line":167,"name":"user click sign up button","match":{"location":"stepDef.WebStep.userClickSignUpButton()"},"keyword":"When "},{"result":{"duration":515675935,"status":"passed"},"line":168,"name":"validation get \"alert\" message \"Sign up successful.\"","match":{"arguments":[{"val":"\"alert\"","offset":15},{"val":"\"Sign up successful.\"","offset":31}],"location":"stepDef.WebStep.validationGetMessage(java.lang.String,java.lang.String)"},"keyword":"Then "},{"result":{"duration":36206113,"status":"passed"},"line":169,"name":"user click login menu","match":{"location":"stepDef.WebStep.userClickLoginMenu()"},"keyword":"And "},{"result":{"duration":252231434,"status":"passed"},"line":170,"name":"user input login username","match":{"location":"stepDef.WebStep.userInputLoginUsername()"},"keyword":"And "},{"result":{"duration":43054152,"status":"passed"},"line":171,"name":"user input login pwd","match":{"location":"stepDef.WebStep.userInputLoginPwd()"},"keyword":"And "},{"result":{"duration":34256729,"status":"passed"},"line":172,"name":"user click login button","match":{"location":"stepDef.WebStep.userClickLoginButton()"},"keyword":"When "},{"result":{"duration":2019129899,"status":"passed"},"line":173,"name":"validation login successful","match":{"location":"stepDef.WebStep.validationLoginSuccessful()"},"keyword":"Then "},{"result":{"duration":174677342,"status":"passed"},"line":174,"name":"user click product name","match":{"location":"stepDef.WebStep.userClickProductName()"},"keyword":"And "},{"result":{"duration":217695937,"status":"passed"},"line":175,"name":"user click add to cart button","match":{"location":"stepDef.WebStep.userClickAddToCartButton()"},"keyword":"And "},{"result":{"duration":515829809,"status":"passed"},"line":176,"name":"validation get \"alert\" message \"Product added.\"","match":{"arguments":[{"val":"\"alert\"","offset":15},{"val":"\"Product added.\"","offset":31}],"location":"stepDef.WebStep.validationGetMessage(java.lang.String,java.lang.String)"},"keyword":"Then "},{"result":{"duration":121872537,"status":"passed"},"line":177,"name":"user click home menu","match":{"location":"stepDef.WebStep.userClickHomeMenu()"},"keyword":"And "},{"result":{"duration":287301603,"status":"passed"},"line":178,"name":"user click product name","match":{"location":"stepDef.WebStep.userClickProductName()"},"keyword":"And "},{"result":{"duration":154252743,"status":"passed"},"line":179,"name":"user click add to cart button","match":{"location":"stepDef.WebStep.userClickAddToCartButton()"},"keyword":"And "},{"result":{"duration":515769797,"status":"passed"},"line":180,"name":"validation get \"alert\" message \"Product added.\"","match":{"arguments":[{"val":"\"alert\"","offset":15},{"val":"\"Product added.\"","offset":31}],"location":"stepDef.WebStep.validationGetMessage(java.lang.String,java.lang.String)"},"keyword":"Then "},{"result":{"duration":179164982,"status":"passed"},"line":181,"name":"user click cart menu","match":{"location":"stepDef.WebStep.userClickCartMenu()"},"keyword":"And "},{"result":{"duration":2010066576,"status":"passed"},"line":182,"name":"validation cart page display equals 2 product","match":{"arguments":[{"val":"2","offset":36}],"location":"stepDef.WebStep.validationCartPageDisplayEqualsProduct(int)"},"keyword":"Then "},{"result":{"duration":32724352,"status":"passed"},"line":183,"name":"validation total price is equals price of product","match":{"location":"stepDef.WebStep.validationTotalPriceIsEqualsPriceOfProduct()"},"keyword":"Then "},{"result":{"duration":33146190,"status":"passed"},"line":184,"name":"user click place order button","match":{"location":"stepDef.WebStep.userClickPlaceOrderButton()"},"keyword":"And "},{"result":{"duration":202842363,"status":"passed"},"line":185,"name":"user click purchase button","match":{"location":"stepDef.WebStep.userClickPurchaseButton()"},"keyword":"And "},{"result":{"duration":13352677,"status":"passed"},"line":186,"name":"validation get \"alert\" message \"Please fill out Name and Creditcard.\"","match":{"arguments":[{"val":"\"alert\"","offset":15},{"val":"\"Please fill out Name and Creditcard.\"","offset":31}],"location":"stepDef.WebStep.validationGetMessage(java.lang.String,java.lang.String)"},"keyword":"Then "}],"tags":[{"name":"@web"}]}],"name":"Test Automation Web","description":"","id":"test-automation-web","keyword":"Feature","uri":"file:src/test/java/features/web.feature","tags":[{"name":"@web","type":"Tag","location":{"line":1,"column":1}}]}]